{
	"animations": [
		{
			"offsets": [
				-21,
				-144
			],
			"cameraOffset": [
				0,
				-20
			],
			"loop": false,
			"fps": 24,
			"anim": "singUP",
			"indices": [],
			"name": "badeline_up"
		},
		{
			"offsets": [
				139,
				-315
			],
			"cameraOffset": [
				-20,
				0
			],
			"loop": false,
			"fps": 24,
			"anim": "singLEFT",
			"indices": [],
			"name": "badeline_left"
		},
		{
			"offsets": [
				4,
				-348
			],
			"cameraOffset": [
				0,
				20
			],
			"loop": false,
			"fps": 24,
			"anim": "singDOWN",
			"indices": [],
			"name": "badeline_down"
		},
		{
			"offsets": [
				-95,
				-265
			],
			"cameraOffset": [
				20,
				0
			],
			"loop": false,
			"fps": 24,
			"anim": "singRIGHT",
			"indices": [],
			"name": "badeline_right"
		},
		{
			"offsets": [
				0,
				-280
			],
			"cameraOffset": [
				20,
				0
			],
			"loop": false,
			"fps": 24,
			"anim": "idle",
			"indices": [],
			"name": "badeline_idle"
		},
		{
			"offsets": [
				83,
				-212
			],
			"cameraOffset": [
				20,
				0
			],
			"loop": false,
			"fps": 24,
			"anim": "hit",
			"indices": [],
			"name": "badeline_hit"
		},
		{
			"loop": true,
			"cameraOffset": [
				20,
				0
			],
			"offsets": [
				83,
				-239
			],
			"anim": "idle-alt",
			"fps": 24,
			"name": "badelinealt_idle",
			"indices": []
		},
		{
			"loop": false,
			"cameraOffset": [
				-20,
				0
			],
			"offsets": [
				210,
				-317
			],
			"anim": "singLEFT-alt",
			"fps": 24,
			"name": "badelinealt_left",
			"indices": []
		},
		{
			"loop": false,
			"cameraOffset": [
				0,
				20
			],
			"offsets": [
				133,
				-358
			],
			"anim": "singDOWN-alt",
			"fps": 24,
			"name": "badelinealt_down",
			"indices": []
		},
		{
			"loop": false,
			"cameraOffset": [
				0,
				-20
			],
			"offsets": [
				77,
				-111
			],
			"anim": "singUP-alt",
			"fps": 24,
			"name": "badelinealt_up",
			"indices": []
		},
		{
			"offsets": [
				-69,
				-285
			],
			"cameraOffset": [
				20,
				0
			],
			"loop": false,
			"fps": 24,
			"anim": "singRIGHT-alt",
			"indices": [],
			"name": "badelinealt_right"
		}
	],
	"no_antialiasing": false,
	"image": "characters/badeline",
	"position": [
		900,
		-60
	],
	"healthicon": "badeline",
	"flip_x": false,
	"healthbar_colors": [
		122,
		71,
		114
	],
	"camera_position": [
		-270,
		300
	],
	"sing_duration": 4,
	"scale": 1
}