{
	"song": {
		"player1": "bf",
		"player2": "documic2",
		"notes": [
			{
				"lengthInSteps": 16,
				"sectionNotes": [],
				"mustHitSection": false
			},
			{
				"lengthInSteps": 16,
				"sectionNotes": [],
				"mustHitSection": false
			},
			{
				"lengthInSteps": 16,
				"sectionNotes": [],
				"mustHitSection": false
			},
			{
				"lengthInSteps": 16,
				"sectionNotes": [],
				"mustHitSection": false
			},
			{
				"lengthInSteps": 16,
				"sectionNotes": [
					[
						7553.95683453237,
						4,
						0,
						"Window Note"
					],
					[
						7580.93525179856,
						5,
						0,
						"Window Note"
					],
					[
						7607.91366906475,
						6,
						0,
						"Window Note"
					],
					[
						7634.89208633094,
						7,
						0,
						"Window Note"
					]
				],
				"bpm": 278,
				"mustHitSection": false,
				"changeBPM": true
			},
			{
				"lengthInSteps": 16,
				"sectionNotes": [
					[
						8201.43884892086,
						2,
						0
					],
					[
						8228.41726618705,
						3,
						0
					],
					[
						8417.26618705036,
						0,
						0
					],
					[
						8552.1582733813,
						1,
						0
					],
					[
						8767.98561151079,
						3,
						0
					],
					[
						9064.74820143885,
						3,
						0
					],
					[
						9064.74820143885,
						1,
						0
					],
					[
						7985.61151079137,
						0,
						0
					],
					[
						8848.92086330935,
						2,
						107.913669064748
					],
					[
						9280.57553956834,
						0,
						107.913669064748
					]
				],
				"bpm": 139,
				"mustHitSection": false,
				"changeBPM": true
			},
			{
				"lengthInSteps": 16,
				"sectionNotes": [
					[
						9928.05755395683,
						2,
						0
					],
					[
						9955.03597122302,
						3,
						0
					],
					[
						10143.8848920863,
						0,
						0
					],
					[
						10278.7769784173,
						1,
						0
					],
					[
						10494.6043165468,
						3,
						0
					],
					[
						10791.3669064748,
						3,
						0
					],
					[
						10791.3669064748,
						1,
						0
					],
					[
						9712.23021582734,
						0,
						0
					],
					[
						10575.5395683453,
						2,
						107.913669064748
					],
					[
						11007.1942446043,
						0,
						107.913669064748
					],
					[
						11007.1942446043,
						5,
						107.913669064748
					]
				],
				"mustHitSection": true
			},
			{
				"lengthInSteps": 16,
				"sectionNotes": [
					[
						11438.8489208633,
						3,
						0
					],
					[
						11357.9136690647,
						2,
						0
					],
					[
						11573.7410071942,
						1,
						0
					],
					[
						11789.5683453237,
						3,
						0
					],
					[
						12086.3309352518,
						0,
						0
					],
					[
						12005.3956834532,
						1,
						0
					],
					[
						12221.2230215827,
						1,
						0
					],
					[
						12302.1582733813,
						2,
						0
					],
					[
						12517.9856115108,
						3,
						0
					],
					[
						12517.9856115108,
						0,
						0
					],
					[
						12652.8776978417,
						2,
						0
					],
					[
						12733.8129496403,
						1,
						0
					],
					[
						12868.7050359712,
						0,
						0
					]
				],
				"mustHitSection": false
			},
			{
				"lengthInSteps": 16,
				"sectionNotes": [
					[
						13165.4676258993,
						3,
						0
					],
					[
						13084.5323741007,
						2,
						0
					],
					[
						13300.3597122302,
						1,
						0
					],
					[
						13516.1870503597,
						3,
						0
					],
					[
						13812.9496402878,
						0,
						0
					],
					[
						13732.0143884892,
						1,
						0
					],
					[
						13947.8417266187,
						1,
						0
					],
					[
						14028.7769784173,
						2,
						0
					],
					[
						14244.6043165468,
						3,
						0
					],
					[
						14244.6043165468,
						0,
						0
					],
					[
						14379.4964028777,
						2,
						0
					],
					[
						14460.4316546763,
						1,
						0
					],
					[
						14595.3237410072,
						0,
						0
					]
				],
				"mustHitSection": true
			},
			{
				"lengthInSteps": 16,
				"sectionNotes": [
					[
						14676.2589928058,
						6,
						0
					],
					[
						14811.1510791367,
						7,
						0
					],
					[
						14892.0863309353,
						5,
						0
					],
					[
						15026.9784172662,
						6,
						0
					],
					[
						15107.9136690647,
						4,
						0
					],
					[
						15242.8057553957,
						5,
						0
					],
					[
						15323.7410071942,
						7,
						0
					],
					[
						14892.0863309353,
						0,
						0
					],
					[
						15323.7410071942,
						2,
						0
					],
					[
						15458.6330935252,
						3,
						0
					],
					[
						15674.4604316547,
						2,
						0
					],
					[
						15755.3956834532,
						0,
						0
					],
					[
						15971.2230215827,
						1,
						0
					],
					[
						15971.2230215827,
						3,
						0
					],
					[
						16187.0503597122,
						2,
						0
					],
					[
						15971.2230215827,
						6,
						0
					],
					[
						15971.2230215827,
						7,
						0
					],
					[
						16187.0503597122,
						4,
						0
					],
					[
						16106.1151079137,
						5,
						0
					],
					[
						16321.9424460432,
						6,
						0
					],
					[
						15107.9136690647,
						1,
						107.913669064748
					]
				],
				"mustHitSection": false
			},
			{
				"lengthInSteps": 16,
				"sectionNotes": [
					[
						16402.8776978417,
						6,
						0
					],
					[
						16537.7697841727,
						7,
						0
					],
					[
						16618.7050359712,
						5,
						0
					],
					[
						16753.5971223022,
						6,
						0
					],
					[
						16834.5323741007,
						4,
						0
					],
					[
						16969.4244604317,
						5,
						0
					],
					[
						17050.3597122302,
						7,
						0
					],
					[
						16618.7050359712,
						0,
						0
					],
					[
						17050.3597122302,
						2,
						0
					],
					[
						17185.2517985611,
						3,
						0
					],
					[
						17401.0791366906,
						2,
						0
					],
					[
						17482.0143884892,
						0,
						0
					],
					[
						17697.8417266187,
						1,
						0
					],
					[
						17697.8417266187,
						3,
						0
					],
					[
						17697.8417266187,
						6,
						0
					],
					[
						17697.8417266187,
						7,
						0
					],
					[
						17913.6690647482,
						4,
						0
					],
					[
						17832.7338129496,
						5,
						0
					],
					[
						18048.5611510791,
						6,
						0
					],
					[
						17185.2517985612,
						6,
						0
					],
					[
						16834.5323741007,
						1,
						107.913669064748
					],
					[
						17913.6690647482,
						2,
						107.913669064748
					]
				],
				"mustHitSection": true
			},
			{
				"lengthInSteps": 16,
				"sectionNotes": [
					[
						18129.4964028777,
						4,
						0
					],
					[
						18264.3884892086,
						5,
						0
					],
					[
						18345.3237410072,
						6,
						0
					],
					[
						18480.2158273381,
						7,
						0
					],
					[
						18561.1510791367,
						6,
						0
					],
					[
						18696.0431654676,
						4,
						0
					],
					[
						18911.8705035971,
						5,
						0
					],
					[
						18992.8057553957,
						7,
						0
					],
					[
						19127.6978417266,
						5,
						0
					],
					[
						19060.2517985611,
						6,
						0
					],
					[
						19208.6330935252,
						4,
						0
					],
					[
						19343.5251798561,
						5,
						0
					],
					[
						19640.2877697842,
						6,
						0
					],
					[
						18129.4964028777,
						0,
						0
					],
					[
						18264.3884892086,
						1,
						0
					],
					[
						18345.3237410072,
						2,
						0
					],
					[
						18480.2158273381,
						3,
						0
					],
					[
						18561.1510791367,
						2,
						0
					],
					[
						18696.0431654676,
						0,
						0
					],
					[
						18911.8705035971,
						1,
						0
					],
					[
						18992.8057553957,
						3,
						0
					],
					[
						19127.6978417266,
						1,
						0
					],
					[
						19060.2517985611,
						2,
						0
					],
					[
						19208.6330935252,
						0,
						0
					],
					[
						19343.5251798561,
						1,
						0
					],
					[
						19640.2877697842,
						2,
						0
					],
					[
						19775.1798561151,
						1,
						0
					],
					[
						19775.1798561151,
						5,
						0
					],
					[
						18776.9784172662,
						2,
						0
					],
					[
						18776.9784172662,
						6,
						0
					],
					[
						19424.4604316547,
						2,
						0
					],
					[
						19424.4604316547,
						6,
						0
					],
					[
						19559.3525179856,
						3,
						0
					],
					[
						19559.3525179856,
						7,
						0
					]
				],
				"mustHitSection": false
			},
			{
				"gfSection": false,
				"lengthInSteps": 16,
				"sectionNotes": [
					[
						19856.1151079137,
						0,
						215.827338129496
					],
					[
						20179.8561151079,
						1,
						0
					],
					[
						19856.1151079137,
						3,
						0
					],
					[
						20179.8561151079,
						2,
						215.827338129496
					],
					[
						20503.5971223022,
						0,
						0
					],
					[
						20503.5971223022,
						3,
						215.827338129496
					],
					[
						21151.0791366906,
						0,
						0
					],
					[
						19856.1151079137,
						4,
						215.827338129496
					],
					[
						20179.8561151079,
						5,
						0
					],
					[
						19856.1151079137,
						7,
						0
					],
					[
						20179.8561151079,
						6,
						215.827338129496
					],
					[
						20503.5971223022,
						4,
						0
					],
					[
						20503.5971223022,
						7,
						215.827338129496
					],
					[
						21151.0791366906,
						4,
						0
					],
					[
						20840.8273381295,
						1,
						204
					],
					[
						20840.8273381295,
						2,
						0
					],
					[
						20840.8273381295,
						5,
						204
					],
					[
						20840.8273381295,
						6,
						0
					],
					[
						21366.9064748201,
						3,
						107.913669064748
					],
					[
						21366.9064748201,
						7,
						107.913669064748
					]
				],
				"mustHitSection": true
			},
			{
				"lengthInSteps": 16,
				"sectionNotes": [
					[
						21582.7338129496,
						1,
						0
					],
					[
						21798.5611510791,
						0,
						0
					],
					[
						22014.3884892086,
						3,
						0
					],
					[
						22149.2805755396,
						0,
						0
					],
					[
						22230.2158273381,
						1,
						0
					],
					[
						22365.1079136691,
						2,
						0
					],
					[
						22580.9352517986,
						3,
						0
					],
					[
						22877.6978417266,
						0,
						0
					],
					[
						23093.5251798561,
						2,
						0
					],
					[
						21582.7338129496,
						2,
						107.913669064748
					],
					[
						22661.8705035971,
						1,
						107.913669064748
					]
				],
				"mustHitSection": false
			},
			{
				"lengthInSteps": 16,
				"sectionNotes": [
					[
						23309.3525179856,
						3,
						0
					],
					[
						23444.2446043166,
						1,
						0
					],
					[
						23525.1798561151,
						0,
						0
					],
					[
						23660.071942446,
						1,
						0
					],
					[
						23741.0071942446,
						2,
						0
					],
					[
						23875.8992805755,
						3,
						0
					],
					[
						23956.8345323741,
						0,
						0
					],
					[
						24091.726618705,
						1,
						0
					],
					[
						24307.5539568345,
						2,
						107.913669064748
					],
					[
						24523.381294964,
						3,
						0
					],
					[
						24604.3165467626,
						2,
						0
					],
					[
						24739.2086330935,
						1,
						130
					],
					[
						24955.035971223,
						0,
						215.827338129496
					]
				],
				"mustHitSection": false
			},
			{
				"lengthInSteps": 16,
				"sectionNotes": [
					[
						25035.9712230216,
						1,
						0
					],
					[
						25251.7985611511,
						0,
						0
					],
					[
						25467.6258992806,
						3,
						0
					],
					[
						25602.5179856115,
						0,
						0
					],
					[
						25683.4532374101,
						1,
						0
					],
					[
						25818.345323741,
						2,
						0
					],
					[
						26034.1726618705,
						3,
						0
					],
					[
						26330.9352517986,
						0,
						0
					],
					[
						26546.7625899281,
						2,
						0
					],
					[
						25035.9712230216,
						2,
						107.913669064748
					],
					[
						26115.1079136691,
						1,
						107.913669064748
					],
					[
						26330.9352517986,
						3,
						0,
						"Window Note"
					]
				],
				"mustHitSection": true
			},
			{
				"lengthInSteps": 16,
				"sectionNotes": [
					[
						26762.5899280576,
						3,
						0
					],
					[
						26897.4820143885,
						1,
						0
					],
					[
						26978.4172661871,
						0,
						0
					],
					[
						27113.309352518,
						1,
						0
					],
					[
						27194.2446043166,
						2,
						0
					],
					[
						27329.1366906475,
						3,
						0
					],
					[
						27410.071942446,
						0,
						0
					],
					[
						27544.964028777,
						1,
						0
					],
					[
						27760.7913669065,
						2,
						107.913669064748
					],
					[
						27976.618705036,
						3,
						0
					],
					[
						28057.5539568345,
						2,
						0
					],
					[
						28408.273381295,
						0,
						215.827338129496
					],
					[
						28192.4460431655,
						1,
						0
					],
					[
						28300.3597122302,
						1,
						0
					]
				],
				"mustHitSection": true
			},
			{
				"lengthInSteps": 16,
				"sectionNotes": [
					[
						28705.035971223,
						3,
						0
					],
					[
						28839.928057554,
						1,
						107.913669064748
					],
					[
						29055.7553956835,
						3,
						0
					],
					[
						29136.690647482,
						2,
						107.913669064748
					],
					[
						29352.5179856115,
						0,
						0
					],
					[
						29487.4100719425,
						2,
						0
					],
					[
						29568.345323741,
						3,
						0
					],
					[
						29703.2374100719,
						1,
						0
					],
					[
						29784.1726618705,
						0,
						0
					],
					[
						30000,
						1,
						107.913669064748
					],
					[
						29568.345323741,
						7,
						0
					],
					[
						29784.1726618705,
						4,
						0
					],
					[
						29784.1726618705,
						6,
						0
					],
					[
						30000,
						5,
						107.913669064748
					],
					[
						28489.2086330935,
						0,
						107.913669064748
					]
				],
				"mustHitSection": false
			},
			{
				"lengthInSteps": 16,
				"sectionNotes": [
					[
						30215.8273381295,
						3,
						0
					],
					[
						30350.7194244604,
						0,
						0
					],
					[
						30431.654676259,
						2,
						0
					],
					[
						30566.5467625899,
						0,
						0
					],
					[
						30647.4820143885,
						3,
						0
					],
					[
						30782.3741007194,
						0,
						0
					],
					[
						30863.309352518,
						1,
						0
					],
					[
						31079.1366906475,
						2,
						107.913669064748
					],
					[
						31294.964028777,
						3,
						0
					],
					[
						31429.8561151079,
						0,
						0
					],
					[
						31429.8561151079,
						1,
						0
					],
					[
						31645.6834532374,
						2,
						107.913669064748
					],
					[
						31861.5107913669,
						0,
						0
					],
					[
						30863.309352518,
						4,
						0
					],
					[
						31079.1366906475,
						6,
						0
					],
					[
						31294.964028777,
						7,
						0
					],
					[
						31510.7913669065,
						5,
						0
					],
					[
						31726.618705036,
						4,
						0
					],
					[
						31861.5107913669,
						6,
						0
					],
					[
						30431.654676259,
						6,
						0,
						"Window Note"
					]
				],
				"mustHitSection": false
			},
			{
				"lengthInSteps": 16,
				"sectionNotes": [
					[
						31942.4460431655,
						7,
						323.741007194245
					],
					[
						31942.4460431655,
						0,
						107.913669064748
					],
					[
						32158.273381295,
						3,
						0
					],
					[
						32293.1654676259,
						1,
						107.913669064748
					],
					[
						32508.9928057554,
						3,
						0
					],
					[
						32589.928057554,
						2,
						107.913669064748
					],
					[
						32805.7553956835,
						0,
						0
					],
					[
						32940.6474820144,
						2,
						0
					],
					[
						33021.582733813,
						3,
						0
					],
					[
						33156.4748201439,
						1,
						0
					],
					[
						33237.4100719425,
						0,
						0
					],
					[
						33453.2374100719,
						1,
						107.913669064748
					],
					[
						33021.582733813,
						7,
						0
					],
					[
						33237.4100719425,
						4,
						0
					],
					[
						33237.4100719425,
						6,
						0
					],
					[
						33453.2374100719,
						5,
						107.913669064748
					]
				],
				"mustHitSection": true
			},
			{
				"lengthInSteps": 16,
				"sectionNotes": [
					[
						33669.0647482014,
						3,
						0
					],
					[
						33803.9568345324,
						0,
						0
					],
					[
						33884.8920863309,
						2,
						0
					],
					[
						34019.7841726619,
						0,
						0
					],
					[
						34100.7194244604,
						3,
						0
					],
					[
						34235.6115107914,
						0,
						0
					],
					[
						34316.5467625899,
						1,
						0
					],
					[
						34532.3741007194,
						2,
						107.913669064748
					],
					[
						34748.2014388489,
						3,
						0
					],
					[
						34883.0935251799,
						0,
						0
					],
					[
						35098.9208633094,
						2,
						107.913669064748
					],
					[
						34316.5467625899,
						4,
						0
					],
					[
						34532.3741007194,
						6,
						0
					],
					[
						34748.2014388489,
						7,
						0
					],
					[
						34883.0935251799,
						5,
						0
					],
					[
						35098.9208633094,
						4,
						107.913669064748
					],
					[
						35314.7482014389,
						6,
						0
					],
					[
						35314.7482014389,
						3,
						0
					],
					[
						33669.0647482015,
						2,
						0
					]
				],
				"mustHitSection": true
			},
			{
				"lengthInSteps": 16,
				"sectionNotes": [
					[
						35395.6834532374,
						3,
						539.568345323741
					],
					[
						35395.6834532374,
						4,
						323.741007194245
					],
					[
						35395.6834532374,
						5,
						0,
						"Window Note"
					]
				],
				"mustHitSection": false
			},
			{
				"lengthInSteps": 16,
				"sectionNotes": [
					[
						37122.3021582734,
						0,
						0
					],
					[
						37553.9568345324,
						2,
						0
					],
					[
						37553.9568345324,
						3,
						0
					],
					[
						37985.6115107914,
						1,
						0
					],
					[
						38201.4388489209,
						2,
						0
					],
					[
						38120.5035971223,
						0,
						0
					],
					[
						38336.3309352518,
						3,
						0
					],
					[
						38552.1582733813,
						0,
						0
					],
					[
						38633.0935251799,
						1,
						0
					],
					[
						38767.9856115108,
						3,
						0
					]
				],
				"mustHitSection": false
			},
			{
				"lengthInSteps": 16,
				"sectionNotes": [
					[
						38983.8129496403,
						2,
						215.827338129496
					],
					[
						39280.5755395684,
						0,
						0
					],
					[
						39280.5755395684,
						3,
						0
					],
					[
						39496.4028776979,
						2,
						0
					],
					[
						39712.2302158274,
						3,
						0
					],
					[
						39847.1223021583,
						1,
						0
					],
					[
						39928.0575539569,
						0,
						0
					],
					[
						40143.8848920864,
						0,
						0
					],
					[
						40359.7122302158,
						1,
						0
					],
					[
						39037.7697841727,
						4,
						0
					],
					[
						39388.4892086331,
						4,
						0
					],
					[
						39712.2302158274,
						4,
						0
					],
					[
						40062.9496402878,
						6,
						0
					],
					[
						40359.7122302158,
						7,
						0
					]
				],
				"mustHitSection": false
			},
			{
				"lengthInSteps": 16,
				"sectionNotes": [
					[
						40575.5395683453,
						6,
						755.395683453237
					],
					[
						40575.5395683453,
						0,
						0
					],
					[
						41007.1942446043,
						2,
						0
					],
					[
						41007.1942446043,
						3,
						0
					],
					[
						41438.8489208633,
						1,
						0
					],
					[
						41654.6762589928,
						2,
						0
					],
					[
						41573.7410071943,
						0,
						0
					],
					[
						41789.5683453238,
						3,
						0
					],
					[
						42005.3956834533,
						0,
						0
					],
					[
						42086.3309352518,
						1,
						0
					],
					[
						42221.2230215828,
						3,
						0
					],
					[
						40791.3669064748,
						1,
						0,
						"Window Note"
					]
				],
				"mustHitSection": true
			},
			{
				"lengthInSteps": 16,
				"sectionNotes": [
					[
						42437.0503597122,
						2,
						215.827338129496
					],
					[
						42733.8129496403,
						0,
						0
					],
					[
						42733.8129496403,
						3,
						0
					],
					[
						42949.6402877698,
						2,
						0
					],
					[
						43165.4676258993,
						3,
						0
					],
					[
						43300.3597122302,
						1,
						0
					],
					[
						43381.2949640288,
						0,
						0
					],
					[
						43597.1223021583,
						0,
						0
					],
					[
						43812.9496402878,
						1,
						0
					]
				],
				"mustHitSection": true
			},
			{
				"lengthInSteps": 16,
				"sectionNotes": [
					[
						44028.7769784173,
						6,
						539.568345323741
					],
					[
						44676.2589928058,
						4,
						0
					],
					[
						45323.7410071943,
						5,
						0
					],
					[
						44460.4316546763,
						2,
						0
					],
					[
						44460.4316546763,
						3,
						0
					],
					[
						44244.6043165468,
						1,
						107.913669064748
					],
					[
						44892.0863309353,
						3,
						0
					],
					[
						45107.9136690648,
						2,
						107.913669064748
					],
					[
						45323.7410071943,
						1,
						107.913669064748
					],
					[
						45539.5683453238,
						0,
						107.913669064748
					],
					[
						44892.0863309353,
						7,
						107.913669064748
					],
					[
						45107.9136690648,
						4,
						107.913669064748
					],
					[
						45539.5683453238,
						6,
						107.913669064748
					],
					[
						44028.7769784173,
						0,
						107.913669064748
					],
					[
						44676.2589928058,
						0,
						107.913669064748
					],
					[
						44892.0863309353,
						5,
						0,
						"Window Note"
					]
				],
				"mustHitSection": false
			},
			{
				"lengthInSteps": 16,
				"sectionNotes": [
					[
						45755.3956834533,
						7,
						0
					],
					[
						45890.2877697842,
						5,
						0
					],
					[
						46187.0503597123,
						4,
						0
					],
					[
						46321.9424460432,
						6,
						0
					],
					[
						46402.8776978418,
						5,
						0
					],
					[
						46537.7697841727,
						7,
						0
					],
					[
						47266.1870503597,
						4,
						0
					],
					[
						45755.3956834533,
						1,
						0
					],
					[
						45890.2877697842,
						3,
						0
					],
					[
						45971.2230215828,
						2,
						0
					],
					[
						46187.0503597123,
						1,
						0
					],
					[
						46321.9424460432,
						3,
						0
					],
					[
						46402.8776978418,
						2,
						0
					],
					[
						45971.2230215828,
						6,
						107.913669064748
					],
					[
						46618.7050359713,
						6,
						107.913669064748
					],
					[
						46834.5323741007,
						4,
						107.913669064748
					],
					[
						47050.3597122302,
						5,
						107.913669064748
					],
					[
						46618.7050359713,
						0,
						107.913669064748
					],
					[
						46834.5323741007,
						1,
						107.913669064748
					],
					[
						47266.1870503597,
						2,
						107.913669064748
					],
					[
						47050.3597122302,
						3,
						107.913669064748
					]
				],
				"mustHitSection": false
			},
			{
				"lengthInSteps": 16,
				"sectionNotes": [
					[
						48129.4964028777,
						4,
						0
					],
					[
						48345.3237410072,
						7,
						0
					],
					[
						48561.1510791367,
						4,
						0
					],
					[
						48776.9784172662,
						5,
						0
					],
					[
						48992.8057553957,
						6,
						0
					],
					[
						47913.6690647482,
						2,
						0
					],
					[
						47913.6690647482,
						3,
						0
					],
					[
						47697.8417266187,
						1,
						107.913669064748
					],
					[
						48129.4964028777,
						0,
						0
					],
					[
						48345.3237410072,
						3,
						0
					],
					[
						48561.1510791367,
						2,
						107.913669064748
					],
					[
						48776.9784172662,
						1,
						107.913669064748
					],
					[
						48992.8057553957,
						0,
						107.913669064748
					],
					[
						47482.0143884892,
						4,
						0
					],
					[
						47859.7122302159,
						4,
						0
					],
					[
						47482.0143884892,
						0,
						107.913669064748
					],
					[
						48776.9784172662,
						3,
						0,
						"Window Note"
					]
				],
				"mustHitSection": true
			},
			{
				"lengthInSteps": 16,
				"sectionNotes": [
					[
						49208.6330935252,
						1,
						0
					],
					[
						49343.5251798561,
						3,
						0
					],
					[
						49424.4604316547,
						2,
						0
					],
					[
						49640.2877697842,
						1,
						0
					],
					[
						49775.1798561151,
						3,
						0
					],
					[
						49856.1151079137,
						2,
						0
					],
					[
						49208.6330935252,
						4,
						0
					],
					[
						49586.3309352518,
						4,
						0
					],
					[
						49856.1151079137,
						4,
						0
					],
					[
						50071.9424460432,
						6,
						0
					],
					[
						50287.7697841727,
						7,
						0
					],
					[
						50503.5971223022,
						4,
						0
					],
					[
						50719.4244604317,
						5,
						0
					],
					[
						50071.9424460432,
						0,
						107.913669064748
					],
					[
						50287.7697841727,
						1,
						107.913669064748
					],
					[
						50503.5971223022,
						3,
						107.913669064748
					],
					[
						50719.4244604317,
						2,
						107.913669064748
					]
				],
				"mustHitSection": true
			},
			{
				"lengthInSteps": 16,
				"sectionNotes": [
					[
						50935.2517985612,
						1,
						0
					],
					[
						51070.1438848921,
						3,
						0
					],
					[
						51151.0791366907,
						0,
						0
					],
					[
						51285.9712230216,
						3,
						0
					],
					[
						51366.9064748202,
						2,
						0
					],
					[
						51501.7985611511,
						0,
						0
					],
					[
						51582.7338129497,
						1,
						0
					],
					[
						51717.6258992806,
						2,
						0
					],
					[
						51798.5611510792,
						3,
						0
					],
					[
						51933.4532374101,
						2,
						0
					],
					[
						52014.3884892087,
						0,
						0
					],
					[
						52149.2805755396,
						1,
						0
					],
					[
						52230.2158273382,
						2,
						0
					],
					[
						52365.1079136691,
						3,
						0
					],
					[
						52446.0431654677,
						2,
						0
					],
					[
						52580.9352517986,
						0,
						0
					]
				],
				"mustHitSection": true
			},
			{
				"lengthInSteps": 16,
				"sectionNotes": [
					[
						52661.8705035972,
						3,
						0
					],
					[
						52877.6978417267,
						0,
						0
					],
					[
						53093.5251798562,
						3,
						0
					],
					[
						53309.3525179856,
						0,
						0
					],
					[
						53525.1798561151,
						1,
						107.913669064748
					],
					[
						53741.0071942446,
						2,
						107.913669064748
					],
					[
						53956.8345323741,
						1,
						107.913669064748
					],
					[
						54172.6618705036,
						3,
						107.913669064748
					]
				],
				"mustHitSection": false
			},
			{
				"lengthInSteps": 16,
				"sectionNotes": [
					[
						54388.4892086331,
						1,
						0
					],
					[
						54523.3812949641,
						3,
						0
					],
					[
						54604.3165467626,
						0,
						0
					],
					[
						54739.2086330936,
						3,
						0
					],
					[
						54820.1438848921,
						2,
						0
					],
					[
						54955.035971223,
						0,
						0
					],
					[
						55035.9712230216,
						1,
						0
					],
					[
						55170.8633093525,
						2,
						0
					],
					[
						55251.7985611511,
						3,
						0
					],
					[
						55386.690647482,
						2,
						0
					],
					[
						55467.6258992806,
						0,
						0
					],
					[
						55602.5179856115,
						1,
						0
					],
					[
						55683.4532374101,
						2,
						0
					],
					[
						55818.345323741,
						3,
						0
					],
					[
						55899.2805755396,
						2,
						0
					],
					[
						56034.1726618705,
						0,
						0
					]
				],
				"mustHitSection": false
			},
			{
				"lengthInSteps": 16,
				"sectionNotes": [
					[
						56115.1079136691,
						3,
						0
					],
					[
						56330.9352517986,
						0,
						0
					],
					[
						56546.7625899281,
						3,
						0
					],
					[
						56762.5899280576,
						0,
						0
					],
					[
						57625.8992805756,
						3,
						107.913669064748
					],
					[
						57194.2446043166,
						2,
						107.913669064748
					],
					[
						57410.0719424461,
						1,
						107.913669064748
					],
					[
						56978.4172661871,
						1,
						107.913669064748
					],
					[
						56546.7625899281,
						2,
						0,
						"Window Note"
					]
				],
				"mustHitSection": true
			},
			{
				"lengthInSteps": 16,
				"sectionNotes": [
					[
						57841.7266187051,
						6,
						755.395683453237
					],
					[
						57841.7266187051,
						2,
						0
					],
					[
						58057.5539568346,
						0,
						0
					],
					[
						58192.4460431655,
						1,
						0
					],
					[
						58408.273381295,
						3,
						0
					],
					[
						58489.2086330936,
						0,
						0
					],
					[
						58624.1007194245,
						3,
						0
					],
					[
						58705.0359712231,
						2,
						0
					],
					[
						58839.928057554,
						0,
						0
					],
					[
						59352.5179856116,
						1,
						0
					],
					[
						58920.8633093526,
						1,
						107.913669064748
					],
					[
						59136.6906474821,
						2,
						107.913669064748
					]
				],
				"mustHitSection": false
			},
			{
				"lengthInSteps": 16,
				"sectionNotes": [
					[
						59568.3453237411,
						3,
						0
					],
					[
						59703.237410072,
						1,
						0
					],
					[
						59784.1726618705,
						0,
						0
					],
					[
						60134.892086331,
						2,
						0
					],
					[
						60215.8273381295,
						0,
						0
					],
					[
						60350.7194244605,
						1,
						0
					],
					[
						60431.654676259,
						2,
						0
					],
					[
						60566.54676259,
						3,
						0
					],
					[
						60647.4820143885,
						2,
						0
					],
					[
						60782.3741007195,
						0,
						0
					],
					[
						60863.309352518,
						2,
						0
					],
					[
						60998.201438849,
						1,
						0
					],
					[
						61079.1366906475,
						3,
						0
					],
					[
						61214.0287769785,
						2,
						0
					]
				],
				"mustHitSection": false
			},
			{
				"lengthInSteps": 16,
				"sectionNotes": [
					[
						61294.964028777,
						4,
						323.741007194245
					],
					[
						61294.964028777,
						2,
						0
					],
					[
						61510.7913669065,
						0,
						0
					],
					[
						61645.6834532374,
						1,
						0
					],
					[
						61861.5107913669,
						3,
						0
					],
					[
						61942.4460431655,
						0,
						0
					],
					[
						62077.3381294964,
						3,
						0
					],
					[
						62158.273381295,
						2,
						0
					],
					[
						62293.1654676259,
						0,
						0
					],
					[
						62805.7553956835,
						1,
						0
					],
					[
						62374.1007194245,
						1,
						107.913669064748
					],
					[
						62589.928057554,
						2,
						107.913669064748
					],
					[
						62158.273381295,
						6,
						0
					],
					[
						62293.1654676259,
						4,
						0
					],
					[
						62374.1007194245,
						5,
						0
					],
					[
						62508.9928057554,
						7,
						0
					],
					[
						62589.928057554,
						5,
						0
					],
					[
						62724.8201438849,
						6,
						0
					],
					[
						62805.7553956835,
						5,
						107.913669064748
					]
				],
				"mustHitSection": true
			},
			{
				"lengthInSteps": 16,
				"sectionNotes": [
					[
						63021.582733813,
						0,
						215.827338129496
					],
					[
						63345.3237410072,
						1,
						0
					],
					[
						63021.582733813,
						3,
						0
					],
					[
						63345.3237410072,
						2,
						215.827338129496
					],
					[
						63669.0647482015,
						0,
						0
					],
					[
						63669.0647482015,
						3,
						215.827338129496
					],
					[
						64316.5467625899,
						0,
						0
					],
					[
						63021.582733813,
						4,
						215.827338129496
					],
					[
						63345.3237410072,
						5,
						0
					],
					[
						63021.582733813,
						7,
						0
					],
					[
						63345.3237410072,
						6,
						215.827338129496
					],
					[
						63669.0647482015,
						4,
						0
					],
					[
						63669.0647482015,
						7,
						215.827338129496
					],
					[
						64316.5467625899,
						4,
						0
					],
					[
						64006.2949640288,
						1,
						204
					],
					[
						64006.2949640288,
						2,
						0
					],
					[
						64006.2949640288,
						5,
						204
					],
					[
						64006.2949640288,
						6,
						0
					],
					[
						64532.3741007195,
						3,
						107.913669064748
					],
					[
						64532.3741007195,
						7,
						107.913669064748
					]
				],
				"mustHitSection": true
			},
			{
				"lengthInSteps": 16,
				"sectionNotes": [
					[
						65179.8561151079,
						2,
						0
					],
					[
						65206.8345323741,
						3,
						0
					],
					[
						65395.6834532374,
						0,
						0
					],
					[
						65530.5755395683,
						1,
						0
					],
					[
						65746.4028776978,
						3,
						0
					],
					[
						66043.1654676259,
						3,
						0
					],
					[
						66043.1654676259,
						1,
						0
					],
					[
						64964.0287769784,
						0,
						0
					],
					[
						65827.3381294964,
						2,
						107.913669064748
					],
					[
						66258.9928057554,
						0,
						107.913669064748
					]
				],
				"mustHitSection": false
			},
			{
				"lengthInSteps": 16,
				"sectionNotes": [
					[
						66906.4748201439,
						2,
						0
					],
					[
						66933.4532374101,
						3,
						0
					],
					[
						67122.3021582733,
						0,
						0
					],
					[
						67257.1942446044,
						1,
						0
					],
					[
						67473.0215827338,
						3,
						0
					],
					[
						67769.7841726618,
						3,
						0
					],
					[
						67769.7841726618,
						1,
						0
					],
					[
						67985.6115107914,
						5,
						0
					],
					[
						66690.6474820144,
						0,
						0
					],
					[
						68120.5035971223,
						4,
						0
					],
					[
						67553.9568345324,
						2,
						107.913669064748
					],
					[
						67985.6115107914,
						0,
						107.913669064748
					],
					[
						67553.9568345324,
						0,
						0,
						"Window Note"
					]
				],
				"mustHitSection": true
			},
			{
				"lengthInSteps": 16,
				"sectionNotes": [
					[
						68417.2661870504,
						3,
						0
					],
					[
						68336.3309352518,
						2,
						0
					],
					[
						68552.1582733812,
						1,
						0
					],
					[
						68767.9856115108,
						3,
						0
					],
					[
						69064.7482014389,
						0,
						0
					],
					[
						68983.8129496402,
						1,
						0
					],
					[
						69199.6402877698,
						1,
						0
					],
					[
						69280.5755395684,
						2,
						0
					],
					[
						69496.4028776979,
						3,
						0
					],
					[
						69496.4028776979,
						0,
						0
					],
					[
						69631.2949640288,
						2,
						0
					],
					[
						69712.2302158274,
						1,
						0
					],
					[
						69847.1223021582,
						0,
						0
					],
					[
						68201.4388489209,
						1,
						0
					],
					[
						69712.2302158274,
						5,
						0
					],
					[
						69847.1223021583,
						4,
						0
					]
				],
				"mustHitSection": false
			},
			{
				"lengthInSteps": 16,
				"sectionNotes": [
					[
						70143.8848920864,
						3,
						0
					],
					[
						70062.9496402877,
						2,
						0
					],
					[
						70278.7769784172,
						1,
						0
					],
					[
						70494.6043165467,
						3,
						0
					],
					[
						70791.3669064748,
						0,
						0
					],
					[
						70710.4316546762,
						1,
						0
					],
					[
						70926.2589928057,
						1,
						0
					],
					[
						71007.1942446044,
						2,
						0
					],
					[
						71223.0215827338,
						3,
						0
					],
					[
						71223.0215827338,
						0,
						0
					],
					[
						71357.9136690647,
						2,
						0
					],
					[
						71438.8489208634,
						1,
						0
					],
					[
						71573.7410071942,
						0,
						0
					],
					[
						69928.0575539569,
						1,
						0
					]
				],
				"mustHitSection": true
			},
			{
				"lengthInSteps": 16,
				"sectionNotes": [
					[
						71654.6762589929,
						6,
						539.568345323741
					],
					[
						72302.1582733813,
						7,
						539.568345323741
					],
					[
						72949.6402877698,
						4,
						0
					],
					[
						73084.5323741008,
						5,
						0
					],
					[
						73165.4676258993,
						6,
						0
					],
					[
						73300.3597122303,
						7,
						0
					],
					[
						71654.6762589929,
						3,
						0
					],
					[
						72005.3956834533,
						3,
						0
					],
					[
						72221.2230215828,
						3,
						0
					],
					[
						72437.0503597123,
						3,
						0
					],
					[
						72517.9856115108,
						1,
						0
					],
					[
						72652.8776978418,
						0,
						0
					],
					[
						72733.8129496403,
						2,
						0
					],
					[
						72868.7050359713,
						3,
						0
					],
					[
						72949.6402877698,
						1,
						0
					],
					[
						73165.4676258993,
						0,
						0
					],
					[
						73300.3597122303,
						1,
						0
					],
					[
						72086.3309352518,
						2,
						0
					],
					[
						72302.1582733813,
						0,
						0
					],
					[
						71978.4172661871,
						5,
						0,
						"Window Note"
					],
					[
						72625.8992805756,
						6,
						0,
						"Window Note"
					]
				],
				"mustHitSection": false
			},
			{
				"lengthInSteps": 16,
				"sectionNotes": [
					[
						73381.2949640288,
						2,
						0
					],
					[
						73516.1870503598,
						3,
						0
					],
					[
						73597.1223021583,
						2,
						0
					],
					[
						73732.0143884893,
						0,
						0
					],
					[
						73812.9496402878,
						1,
						0
					],
					[
						73812.9496402878,
						2,
						0
					],
					[
						73947.8417266188,
						3,
						0
					],
					[
						74028.7769784173,
						2,
						0
					],
					[
						74163.6690647482,
						0,
						0
					],
					[
						74244.6043165468,
						1,
						0
					],
					[
						74379.4964028777,
						3,
						0
					],
					[
						74460.4316546763,
						2,
						0
					],
					[
						74595.3237410072,
						0,
						0
					],
					[
						74527.8776978418,
						1,
						0
					],
					[
						74676.2589928058,
						2,
						0
					],
					[
						74811.1510791367,
						1,
						0
					],
					[
						74892.0863309353,
						3,
						0
					],
					[
						75026.9784172662,
						0,
						0
					],
					[
						73381.2949640288,
						6,
						0
					],
					[
						73516.1870503598,
						7,
						0
					],
					[
						73597.1223021583,
						6,
						0
					],
					[
						73732.0143884893,
						4,
						0
					],
					[
						73812.9496402878,
						5,
						0
					],
					[
						73812.9496402878,
						6,
						0
					],
					[
						73947.8417266188,
						7,
						0
					],
					[
						74028.7769784173,
						6,
						0
					],
					[
						74163.6690647482,
						4,
						0
					],
					[
						74244.6043165468,
						5,
						0
					],
					[
						74379.4964028777,
						7,
						0
					],
					[
						74460.4316546763,
						6,
						0
					],
					[
						74595.3237410072,
						4,
						0
					],
					[
						74527.8776978418,
						5,
						0
					],
					[
						74676.2589928058,
						6,
						0
					],
					[
						74811.1510791367,
						5,
						0
					],
					[
						74892.0863309353,
						7,
						0
					],
					[
						75026.9784172662,
						4,
						0
					]
				],
				"mustHitSection": false
			},
			{
				"lengthInSteps": 16,
				"sectionNotes": [
					[
						75107.9136690648,
						6,
						539.568345323741
					],
					[
						75755.3956834533,
						7,
						539.568345323741
					],
					[
						76402.8776978418,
						4,
						0
					],
					[
						76537.7697841727,
						5,
						0
					],
					[
						76618.7050359713,
						6,
						0
					],
					[
						76753.5971223022,
						7,
						0
					],
					[
						75107.9136690648,
						3,
						0
					],
					[
						75458.6330935252,
						3,
						0
					],
					[
						75674.4604316547,
						3,
						0
					],
					[
						75890.2877697842,
						3,
						0
					],
					[
						75971.2230215828,
						1,
						0
					],
					[
						76106.1151079137,
						0,
						0
					],
					[
						76187.0503597123,
						2,
						0
					],
					[
						76321.9424460432,
						3,
						0
					],
					[
						76402.8776978418,
						1,
						0
					],
					[
						76618.7050359713,
						0,
						0
					],
					[
						76753.5971223022,
						1,
						0
					],
					[
						75539.5683453238,
						2,
						0
					],
					[
						75755.3956834533,
						0,
						0
					]
				],
				"mustHitSection": true
			},
			{
				"lengthInSteps": 16,
				"sectionNotes": [
					[
						76834.5323741008,
						2,
						0
					],
					[
						76969.4244604317,
						3,
						0
					],
					[
						77050.3597122303,
						2,
						0
					],
					[
						77185.2517985612,
						0,
						0
					],
					[
						77266.1870503598,
						1,
						0
					],
					[
						77266.1870503598,
						2,
						0
					],
					[
						77401.0791366907,
						3,
						0
					],
					[
						77482.0143884893,
						2,
						0
					],
					[
						77616.9064748202,
						0,
						0
					],
					[
						77697.8417266188,
						1,
						0
					],
					[
						77832.7338129497,
						3,
						0
					],
					[
						77913.6690647483,
						2,
						0
					],
					[
						78048.5611510792,
						0,
						0
					],
					[
						77981.1151079137,
						1,
						0
					],
					[
						78129.4964028777,
						2,
						0
					],
					[
						78264.3884892087,
						1,
						0
					],
					[
						78345.3237410072,
						3,
						0
					],
					[
						78480.2158273382,
						0,
						0
					],
					[
						76834.5323741008,
						6,
						0
					],
					[
						76969.4244604317,
						7,
						0
					],
					[
						77050.3597122303,
						6,
						0
					],
					[
						77185.2517985612,
						4,
						0
					],
					[
						77266.1870503598,
						5,
						0
					],
					[
						77266.1870503598,
						6,
						0
					],
					[
						77401.0791366907,
						7,
						0
					],
					[
						77482.0143884893,
						6,
						0
					],
					[
						77616.9064748202,
						4,
						0
					],
					[
						77697.8417266188,
						5,
						0
					],
					[
						77832.7338129497,
						7,
						0
					],
					[
						77913.6690647483,
						6,
						0
					],
					[
						78048.5611510792,
						4,
						0
					],
					[
						77981.1151079137,
						5,
						0
					],
					[
						78129.4964028777,
						6,
						0
					],
					[
						78264.3884892087,
						5,
						0
					],
					[
						78345.3237410072,
						7,
						0
					],
					[
						78480.2158273382,
						4,
						0
					]
				],
				"mustHitSection": true
			},
			{
				"lengthInSteps": 16,
				"sectionNotes": [
					[
						78561.1510791367,
						2,
						215.827338129496
					],
					[
						78884.892086331,
						3,
						215.827338129496
					],
					[
						79424.4604316547,
						2,
						0
					],
					[
						79208.6330935252,
						0,
						107.913669064748
					],
					[
						79424.4604316547,
						1,
						107.913669064748
					],
					[
						79640.2877697842,
						3,
						107.913669064748
					],
					[
						79856.1151079137,
						1,
						107.913669064748
					],
					[
						80071.9424460432,
						3,
						107.913669064748
					]
				],
				"mustHitSection": false
			},
			{
				"lengthInSteps": 16,
				"sectionNotes": [
					[
						81501.7985611511,
						2,
						215.827338129496
					],
					[
						81151.0791366907,
						3,
						269.78417266187
					],
					[
						81798.5611510792,
						0,
						269.78417266187
					],
					[
						80287.7697841727,
						2,
						107.913669064748
					],
					[
						80503.5971223022,
						0,
						107.913669064748
					],
					[
						80719.4244604317,
						1,
						107.913669064748
					],
					[
						80935.2517985612,
						2,
						107.913669064748
					]
				],
				"mustHitSection": false
			},
			{
				"lengthInSteps": 16,
				"sectionNotes": [
					[
						82014.3884892087,
						2,
						215.827338129496
					],
					[
						82338.1294964029,
						3,
						215.827338129496
					],
					[
						83525.1798561152,
						3,
						107.913669064748
					],
					[
						82877.6978417267,
						2,
						0
					],
					[
						82176.2589928058,
						5,
						1079.13669064748
					],
					[
						83525.1798561152,
						7,
						0
					],
					[
						82661.8705035972,
						0,
						107.913669064748
					],
					[
						82877.6978417267,
						1,
						107.913669064748
					],
					[
						83093.5251798562,
						3,
						107.913669064748
					],
					[
						83309.3525179857,
						1,
						107.913669064748
					],
					[
						82446.0431654677,
						1,
						0,
						"Window Note"
					]
				],
				"mustHitSection": true
			},
			{
				"lengthInSteps": 16,
				"sectionNotes": [
					[
						84955.0359712231,
						2,
						215.827338129496
					],
					[
						83741.0071942447,
						4,
						0
					],
					[
						83956.8345323742,
						7,
						0
					],
					[
						84172.6618705037,
						4,
						0
					],
					[
						84307.5539568346,
						7,
						0
					],
					[
						84388.4892086332,
						6,
						0
					],
					[
						84604.3165467627,
						3,
						269.78417266187
					],
					[
						85251.7985611511,
						0,
						269.78417266187
					],
					[
						84388.4892086332,
						2,
						107.913669064748
					],
					[
						84172.6618705037,
						1,
						107.913669064748
					],
					[
						83956.8345323742,
						0,
						107.913669064748
					],
					[
						83741.0071942447,
						2,
						107.913669064748
					],
					[
						84604.3165467627,
						5,
						107.913669064748
					],
					[
						84820.1438848922,
						4,
						107.913669064748
					],
					[
						85035.9712230216,
						5,
						107.913669064748
					],
					[
						85251.7985611511,
						7,
						107.913669064748
					],
					[
						84820.1438848922,
						0,
						0,
						"Window Note"
					]
				],
				"mustHitSection": true
			},
			{
				"lengthInSteps": 16,
				"sectionNotes": [
					[
						85629.4964028778,
						5,
						647.482014388489
					],
					[
						85467.6258992806,
						2,
						0
					],
					[
						85602.5179856116,
						1,
						0
					],
					[
						85683.4532374101,
						0,
						0
					],
					[
						85899.2805755396,
						2,
						0
					],
					[
						85899.2805755396,
						3,
						0
					],
					[
						86115.1079136691,
						0,
						107.913669064748
					],
					[
						86330.9352517986,
						1,
						0
					],
					[
						86465.8273381296,
						3,
						0
					],
					[
						86546.7625899281,
						2,
						0
					],
					[
						86681.6546762591,
						1,
						0
					],
					[
						86762.5899280576,
						0,
						0
					],
					[
						86897.4820143886,
						2,
						0
					],
					[
						86978.4172661871,
						3,
						0
					],
					[
						87113.309352518,
						0,
						0
					]
				],
				"mustHitSection": false
			},
			{
				"lengthInSteps": 16,
				"sectionNotes": [
					[
						87194.2446043166,
						5,
						323.741007194245
					],
					[
						87194.2446043166,
						2,
						0
					],
					[
						87329.1366906475,
						1,
						0
					],
					[
						87410.0719424461,
						0,
						0
					],
					[
						87625.8992805756,
						2,
						0
					],
					[
						87625.8992805756,
						3,
						0
					],
					[
						87841.7266187051,
						0,
						107.913669064748
					],
					[
						88057.5539568346,
						1,
						0
					],
					[
						88192.4460431655,
						3,
						0
					],
					[
						88273.3812949641,
						2,
						0
					],
					[
						88408.273381295,
						1,
						0
					],
					[
						88489.2086330936,
						0,
						0
					],
					[
						88624.1007194245,
						2,
						0
					],
					[
						88705.0359712231,
						3,
						0
					],
					[
						88839.928057554,
						0,
						0
					]
				],
				"mustHitSection": true
			},
			{
				"lengthInSteps": 16,
				"sectionNotes": [
					[
						88920.8633093526,
						5,
						0
					],
					[
						89055.7553956835,
						7,
						0
					],
					[
						89136.6906474821,
						6,
						0
					],
					[
						89271.582733813,
						4,
						0
					],
					[
						89352.5179856116,
						6,
						0
					],
					[
						89487.4100719425,
						7,
						0
					],
					[
						89568.3453237411,
						5,
						0
					],
					[
						89703.237410072,
						4,
						0
					],
					[
						89784.1726618706,
						6,
						0
					],
					[
						89919.0647482015,
						5,
						0
					],
					[
						90000.0000000001,
						7,
						0
					],
					[
						90134.892086331,
						6,
						0
					],
					[
						90215.8273381296,
						5,
						0
					],
					[
						90350.7194244605,
						4,
						0
					],
					[
						90431.6546762591,
						6,
						0
					],
					[
						90566.54676259,
						7,
						0
					],
					[
						88920.8633093526,
						2,
						0
					],
					[
						89055.7553956835,
						0,
						0
					],
					[
						89136.6906474821,
						1,
						0
					],
					[
						89271.582733813,
						3,
						0
					],
					[
						89352.5179856116,
						2,
						107.913669064748
					],
					[
						89568.3453237411,
						1,
						0
					],
					[
						89703.237410072,
						3,
						0
					],
					[
						89784.1726618706,
						1,
						0
					],
					[
						89919.0647482015,
						2,
						0
					],
					[
						90000.0000000001,
						0,
						107.913669064748
					],
					[
						90215.8273381296,
						1,
						107.913669064748
					],
					[
						90431.6546762591,
						3,
						107.913669064748
					]
				],
				"mustHitSection": false
			},
			{
				"lengthInSteps": 16,
				"sectionNotes": [
					[
						90647.4820143886,
						0,
						107.913669064748
					],
					[
						90863.3093525181,
						2,
						107.913669064748
					],
					[
						91079.1366906475,
						1,
						107.913669064748
					],
					[
						91294.964028777,
						3,
						107.913669064748
					],
					[
						91726.618705036,
						0,
						107.913669064748
					],
					[
						91510.7913669065,
						2,
						0
					],
					[
						91618.7050359713,
						1,
						0
					],
					[
						91942.4460431655,
						2,
						0
					],
					[
						92050.3597122303,
						3,
						0
					],
					[
						92158.273381295,
						0,
						0
					],
					[
						92266.1870503598,
						1,
						0
					],
					[
						90647.4820143886,
						6,
						107.913669064748
					],
					[
						90863.3093525181,
						4,
						107.913669064748
					],
					[
						91079.1366906475,
						7,
						0
					],
					[
						91214.0287769785,
						6,
						0
					],
					[
						91294.964028777,
						5,
						0
					],
					[
						91429.856115108,
						4,
						0
					],
					[
						91510.7913669065,
						6,
						107.913669064748
					],
					[
						91726.618705036,
						7,
						107.913669064748
					],
					[
						91942.4460431655,
						6,
						107.913669064748
					],
					[
						92158.273381295,
						5,
						107.913669064748
					],
					[
						91294.964028777,
						0,
						0,
						"Window Note"
					]
				],
				"mustHitSection": true
			},
			{
				"lengthInSteps": 16,
				"sectionNotes": [
					[
						92805.7553956834,
						2,
						0
					],
					[
						92832.7338129496,
						3,
						0
					],
					[
						93021.5827338129,
						0,
						0
					],
					[
						93156.4748201439,
						1,
						0
					],
					[
						93372.3021582734,
						3,
						0
					],
					[
						93669.0647482014,
						3,
						0
					],
					[
						93669.0647482014,
						1,
						0
					],
					[
						92589.9280575539,
						0,
						0
					],
					[
						93453.237410072,
						2,
						107.913669064748
					],
					[
						93884.892086331,
						0,
						107.913669064748
					]
				],
				"mustHitSection": false
			},
			{
				"lengthInSteps": 16,
				"sectionNotes": [
					[
						94532.3741007194,
						2,
						0
					],
					[
						94559.3525179856,
						3,
						0
					],
					[
						94748.2014388489,
						0,
						0
					],
					[
						94883.0935251799,
						1,
						0
					],
					[
						95098.9208633094,
						3,
						0
					],
					[
						95395.6834532374,
						3,
						0
					],
					[
						95395.6834532374,
						1,
						0
					],
					[
						94316.5467625899,
						0,
						0
					],
					[
						95179.856115108,
						2,
						107.913669064748
					],
					[
						95611.510791367,
						0,
						107.913669064748
					],
					[
						95611.510791367,
						5,
						107.913669064748
					],
					[
						95179.856115108,
						0,
						0,
						"Window Note"
					]
				],
				"mustHitSection": true
			},
			{
				"lengthInSteps": 16,
				"sectionNotes": [
					[
						96043.1654676259,
						3,
						0
					],
					[
						95962.2302158273,
						2,
						0
					],
					[
						96178.0575539568,
						1,
						0
					],
					[
						96393.8848920863,
						3,
						0
					],
					[
						96690.6474820144,
						0,
						0
					],
					[
						96609.7122302158,
						1,
						0
					],
					[
						96825.5395683453,
						1,
						0
					],
					[
						96906.4748201439,
						2,
						0
					],
					[
						97122.3021582734,
						3,
						0
					],
					[
						97122.3021582734,
						0,
						0
					],
					[
						97257.1942446043,
						2,
						0
					],
					[
						97338.1294964029,
						1,
						0
					],
					[
						97473.0215827338,
						0,
						0
					],
					[
						97338.129496403,
						5,
						107.913669064748
					]
				],
				"mustHitSection": false
			},
			{
				"lengthInSteps": 16,
				"sectionNotes": [
					[
						97769.7841726619,
						3,
						0
					],
					[
						97688.8489208633,
						2,
						0
					],
					[
						97904.6762589928,
						1,
						0
					],
					[
						98120.5035971223,
						3,
						0
					],
					[
						98417.2661870504,
						0,
						0
					],
					[
						98336.3309352518,
						1,
						0
					],
					[
						98552.1582733813,
						1,
						0
					],
					[
						98633.0935251799,
						2,
						0
					],
					[
						98848.9208633094,
						3,
						0
					],
					[
						98848.9208633094,
						0,
						0
					],
					[
						98983.8129496403,
						2,
						0
					],
					[
						99064.7482014389,
						1,
						0
					],
					[
						99199.6402877698,
						0,
						0
					]
				],
				"mustHitSection": true
			},
			{
				"lengthInSteps": 16,
				"sectionNotes": [
					[
						99280.5755395684,
						2,
						0
					],
					[
						99415.4676258993,
						3,
						0
					],
					[
						99496.4028776979,
						1,
						0
					],
					[
						99631.2949640288,
						2,
						0
					],
					[
						99712.2302158273,
						0,
						0
					],
					[
						99847.1223021583,
						1,
						0
					],
					[
						99928.0575539568,
						3,
						0
					],
					[
						100062.949640288,
						2,
						0
					],
					[
						100143.884892086,
						1,
						215.827338129496
					],
					[
						100467.625899281,
						0,
						215.827338129496
					],
					[
						100791.366906475,
						2,
						107.913669064748
					],
					[
						99280.5755395684,
						6,
						215.827338129496
					],
					[
						99280.5755395684,
						7,
						0,
						"Window Note"
					]
				],
				"mustHitSection": false
			},
			{
				"sectionNotes": [
					[
						101007.194244604,
						2,
						0
					],
					[
						101142.086330935,
						3,
						0
					],
					[
						101223.021582734,
						1,
						0
					],
					[
						101357.913669065,
						2,
						0
					],
					[
						101438.848920863,
						0,
						0
					],
					[
						101573.741007194,
						1,
						0
					],
					[
						101654.676258993,
						3,
						0
					],
					[
						101789.568345324,
						2,
						0
					],
					[
						101870.503597122,
						1,
						215.827338129496
					],
					[
						102194.244604317,
						0,
						215.827338129496
					],
					[
						102517.985611511,
						2,
						107.913669064748
					],
					[
						101007.194244604,
						7,
						755.395683453237
					],
					[
						102517.985611511,
						6,
						0
					],
					[
						102652.877697842,
						6,
						0
					],
					[
						102194.244604317,
						3,
						0,
						"Window Note"
					]
				],
				"typeOfSection": 0,
				"lengthInSteps": 16,
				"gfSection": false,
				"altAnim": false,
				"mustHitSection": true,
				"changeBPM": false,
				"bpm": 144
			},
			{
				"sectionNotes": [
					[
						102733.81294964,
						7,
						755.395683453237
					],
					[
						102733.81294964,
						0,
						215.827338129496
					],
					[
						103111.510791367,
						3,
						215.827338129496
					],
					[
						103408.273381295,
						0,
						107.913669064748
					],
					[
						103597.122302158,
						1,
						0
					],
					[
						103732.014388489,
						2,
						0
					],
					[
						103812.949640288,
						3,
						107.913669064748
					],
					[
						104028.776978417,
						2,
						107.913669064748
					],
					[
						104244.604316547,
						0,
						107.913669064748
					],
					[
						104244.604316547,
						6,
						0
					],
					[
						104379.496402878,
						6,
						0
					]
				],
				"typeOfSection": 0,
				"lengthInSteps": 16,
				"gfSection": false,
				"altAnim": false,
				"mustHitSection": false,
				"changeBPM": false,
				"bpm": 139
			},
			{
				"sectionNotes": [
					[
						104460.431654676,
						0,
						215.827338129496
					],
					[
						104838.129496403,
						3,
						215.827338129496
					],
					[
						105134.892086331,
						0,
						107.913669064748
					],
					[
						105323.741007194,
						1,
						0
					],
					[
						105458.633093525,
						2,
						0
					],
					[
						105539.568345324,
						3,
						107.913669064748
					],
					[
						105755.395683453,
						2,
						107.913669064748
					],
					[
						105971.223021583,
						0,
						107.913669064748
					],
					[
						104676.258992806,
						5,
						0
					],
					[
						104892.086330935,
						5,
						107.913669064748
					],
					[
						105107.913669065,
						6,
						107.913669064748
					],
					[
						105323.741007194,
						7,
						0
					],
					[
						105458.633093525,
						5,
						0
					],
					[
						105539.568345324,
						4,
						107.913669064748
					],
					[
						105755.395683453,
						5,
						107.913669064748
					],
					[
						105971.223021583,
						7,
						107.913669064748
					],
					[
						104892.086330935,
						1,
						0,
						"Window Note"
					]
				],
				"typeOfSection": 0,
				"lengthInSteps": 16,
				"gfSection": false,
				"altAnim": false,
				"mustHitSection": true,
				"changeBPM": false,
				"bpm": 139
			},
			{
				"sectionNotes": [
					[
						106187.050359712,
						5,
						0
					],
					[
						106187.050359712,
						6,
						2050.35971223021
					],
					[
						106187.050359712,
						1,
						0
					],
					[
						106187.050359712,
						2,
						539.568345323741
					],
					[
						106834.532374101,
						0,
						1402.87769784173
					],
					[
						106618.705035971,
						3,
						0,
						"Window Note"
					],
					[
						107482.014388489,
						1,
						0,
						"Window Note"
					],
					[
						107050.35971223,
						2,
						0,
						"Window Note"
					]
				],
				"typeOfSection": 0,
				"lengthInSteps": 16,
				"gfSection": false,
				"altAnim": false,
				"mustHitSection": true,
				"changeBPM": false,
				"bpm": 139
			},
			{
				"sectionNotes": [],
				"typeOfSection": 0,
				"lengthInSteps": 16,
				"gfSection": false,
				"altAnim": false,
				"mustHitSection": true,
				"changeBPM": false,
				"bpm": 139
			},
			{
				"sectionNotes": [],
				"typeOfSection": 0,
				"lengthInSteps": 16,
				"gfSection": false,
				"altAnim": false,
				"mustHitSection": false,
				"changeBPM": false,
				"bpm": 139
			},
			{
				"sectionNotes": [],
				"typeOfSection": 0,
				"lengthInSteps": 16,
				"gfSection": false,
				"altAnim": false,
				"mustHitSection": false,
				"changeBPM": false,
				"bpm": 139
			},
			{
				"sectionNotes": [],
				"typeOfSection": 0,
				"lengthInSteps": 16,
				"gfSection": false,
				"altAnim": false,
				"mustHitSection": true,
				"changeBPM": false,
				"bpm": 139
			},
			{
				"sectionNotes": [],
				"typeOfSection": 0,
				"lengthInSteps": 16,
				"gfSection": false,
				"altAnim": false,
				"mustHitSection": true,
				"changeBPM": false,
				"bpm": 139
			},
			{
				"sectionNotes": [],
				"typeOfSection": 0,
				"lengthInSteps": 16,
				"gfSection": false,
				"altAnim": false,
				"mustHitSection": false,
				"changeBPM": false,
				"bpm": 139
			},
			{
				"lengthInSteps": 16,
				"typeOfSection": 0,
				"sectionNotes": [],
				"altAnim": false,
				"gfSection": false,
				"bpm": 139,
				"changeBPM": false,
				"mustHitSection": false
			},
			{
				"lengthInSteps": 16,
				"typeOfSection": 0,
				"sectionNotes": [],
				"altAnim": false,
				"gfSection": false,
				"bpm": 139,
				"changeBPM": false,
				"mustHitSection": false
			},
			{
				"lengthInSteps": 16,
				"typeOfSection": 0,
				"sectionNotes": [],
				"altAnim": false,
				"gfSection": false,
				"bpm": 139,
				"changeBPM": false,
				"mustHitSection": true
			},
			{
				"lengthInSteps": 16,
				"typeOfSection": 0,
				"sectionNotes": [],
				"altAnim": false,
				"gfSection": false,
				"bpm": 139,
				"changeBPM": false,
				"mustHitSection": true
			},
			{
				"lengthInSteps": 16,
				"typeOfSection": 0,
				"sectionNotes": [],
				"altAnim": false,
				"gfSection": false,
				"bpm": 139,
				"changeBPM": false,
				"mustHitSection": true
			},
			{
				"lengthInSteps": 16,
				"typeOfSection": 0,
				"sectionNotes": [],
				"altAnim": false,
				"gfSection": false,
				"bpm": 139,
				"changeBPM": false,
				"mustHitSection": true
			},
			{
				"lengthInSteps": 16,
				"typeOfSection": 0,
				"sectionNotes": [],
				"altAnim": false,
				"gfSection": false,
				"bpm": 139,
				"changeBPM": false,
				"mustHitSection": true
			},
			{
				"lengthInSteps": 16,
				"typeOfSection": 0,
				"sectionNotes": [],
				"altAnim": false,
				"gfSection": false,
				"bpm": 139,
				"changeBPM": false,
				"mustHitSection": true
			},
			{
				"lengthInSteps": 16,
				"typeOfSection": 0,
				"sectionNotes": [],
				"altAnim": false,
				"gfSection": false,
				"bpm": 139,
				"changeBPM": false,
				"mustHitSection": true
			},
			{
				"sectionNotes": [],
				"typeOfSection": 0,
				"lengthInSteps": 16,
				"gfSection": false,
				"altAnim": false,
				"mustHitSection": true,
				"changeBPM": false,
				"bpm": 139
			},
			{
				"lengthInSteps": 16,
				"typeOfSection": 0,
				"sectionNotes": [],
				"altAnim": false,
				"gfSection": false,
				"bpm": 139,
				"changeBPM": false,
				"mustHitSection": true
			},
			{
				"lengthInSteps": 16,
				"typeOfSection": 0,
				"sectionNotes": [],
				"altAnim": false,
				"gfSection": false,
				"bpm": 139,
				"changeBPM": false,
				"mustHitSection": true
			},
			{
				"lengthInSteps": 16,
				"typeOfSection": 0,
				"sectionNotes": [],
				"altAnim": false,
				"gfSection": false,
				"bpm": 139,
				"changeBPM": false,
				"mustHitSection": true
			},
			{
				"lengthInSteps": 16,
				"typeOfSection": 0,
				"sectionNotes": [],
				"altAnim": false,
				"gfSection": false,
				"bpm": 139,
				"changeBPM": false,
				"mustHitSection": true
			},
			{
				"lengthInSteps": 16,
				"typeOfSection": 0,
				"sectionNotes": [],
				"altAnim": false,
				"gfSection": false,
				"bpm": 139,
				"changeBPM": false,
				"mustHitSection": true
			},
			{
				"sectionNotes": [],
				"typeOfSection": 0,
				"lengthInSteps": 16,
				"gfSection": false,
				"altAnim": false,
				"mustHitSection": true,
				"changeBPM": false,
				"bpm": 139
			},
			{
				"sectionNotes": [],
				"typeOfSection": 0,
				"lengthInSteps": 16,
				"gfSection": false,
				"altAnim": false,
				"mustHitSection": true,
				"changeBPM": false,
				"bpm": 139
			},
			{
				"sectionNotes": [],
				"typeOfSection": 0,
				"lengthInSteps": 16,
				"gfSection": false,
				"altAnim": false,
				"mustHitSection": true,
				"changeBPM": false,
				"bpm": 139
			},
			{
				"lengthInSteps": 16,
				"typeOfSection": 0,
				"sectionNotes": [],
				"altAnim": false,
				"gfSection": false,
				"bpm": 139,
				"changeBPM": false,
				"mustHitSection": true
			},
			{
				"lengthInSteps": 16,
				"typeOfSection": 0,
				"sectionNotes": [],
				"altAnim": false,
				"gfSection": false,
				"bpm": 139,
				"changeBPM": false,
				"mustHitSection": true
			},
			{
				"lengthInSteps": 16,
				"typeOfSection": 0,
				"sectionNotes": [],
				"altAnim": false,
				"gfSection": false,
				"bpm": 139,
				"changeBPM": false,
				"mustHitSection": true
			},
			{
				"sectionNotes": [],
				"typeOfSection": 0,
				"lengthInSteps": 16,
				"gfSection": false,
				"altAnim": false,
				"mustHitSection": true,
				"changeBPM": false,
				"bpm": 139
			},
			{
				"sectionNotes": [],
				"typeOfSection": 0,
				"lengthInSteps": 16,
				"gfSection": false,
				"altAnim": false,
				"mustHitSection": true,
				"changeBPM": false,
				"bpm": 139
			},
			{
				"sectionNotes": [],
				"typeOfSection": 0,
				"lengthInSteps": 16,
				"gfSection": false,
				"altAnim": false,
				"mustHitSection": true,
				"changeBPM": false,
				"bpm": 139
			},
			{
				"sectionNotes": [],
				"typeOfSection": 0,
				"lengthInSteps": 16,
				"gfSection": false,
				"altAnim": false,
				"mustHitSection": true,
				"changeBPM": false,
				"bpm": 139
			},
			{
				"sectionNotes": [],
				"typeOfSection": 0,
				"lengthInSteps": 16,
				"gfSection": false,
				"altAnim": false,
				"mustHitSection": true,
				"changeBPM": false,
				"bpm": 139
			},
			{
				"sectionNotes": [],
				"typeOfSection": 0,
				"lengthInSteps": 16,
				"gfSection": false,
				"altAnim": false,
				"mustHitSection": true,
				"changeBPM": false,
				"bpm": 139
			},
			{
				"sectionNotes": [],
				"typeOfSection": 0,
				"lengthInSteps": 16,
				"gfSection": false,
				"altAnim": false,
				"mustHitSection": true,
				"changeBPM": false,
				"bpm": 139
			},
			{
				"sectionNotes": [],
				"typeOfSection": 0,
				"lengthInSteps": 16,
				"gfSection": false,
				"altAnim": false,
				"mustHitSection": true,
				"changeBPM": false,
				"bpm": 139
			},
			{
				"sectionNotes": [],
				"typeOfSection": 0,
				"lengthInSteps": 16,
				"gfSection": false,
				"altAnim": false,
				"mustHitSection": true,
				"changeBPM": false,
				"bpm": 139
			},
			{
				"lengthInSteps": 16,
				"typeOfSection": 0,
				"sectionNotes": [],
				"altAnim": false,
				"gfSection": false,
				"bpm": 139,
				"changeBPM": false,
				"mustHitSection": true
			},
			{
				"lengthInSteps": 16,
				"typeOfSection": 0,
				"sectionNotes": [],
				"altAnim": false,
				"gfSection": false,
				"bpm": 139,
				"changeBPM": false,
				"mustHitSection": true
			},
			{
				"lengthInSteps": 16,
				"typeOfSection": 0,
				"sectionNotes": [],
				"altAnim": false,
				"gfSection": false,
				"bpm": 139,
				"changeBPM": false,
				"mustHitSection": true
			},
			{
				"lengthInSteps": 16,
				"typeOfSection": 0,
				"sectionNotes": [],
				"altAnim": false,
				"gfSection": false,
				"bpm": 139,
				"changeBPM": false,
				"mustHitSection": true
			},
			{
				"lengthInSteps": 16,
				"typeOfSection": 0,
				"sectionNotes": [],
				"altAnim": false,
				"gfSection": false,
				"bpm": 139,
				"changeBPM": false,
				"mustHitSection": true
			},
			{
				"lengthInSteps": 16,
				"typeOfSection": 0,
				"sectionNotes": [],
				"altAnim": false,
				"gfSection": false,
				"bpm": 139,
				"changeBPM": false,
				"mustHitSection": true
			},
			{
				"lengthInSteps": 16,
				"typeOfSection": 0,
				"sectionNotes": [],
				"altAnim": false,
				"gfSection": false,
				"bpm": 139,
				"changeBPM": false,
				"mustHitSection": true
			},
			{
				"sectionNotes": [],
				"typeOfSection": 0,
				"lengthInSteps": 16,
				"gfSection": false,
				"altAnim": false,
				"mustHitSection": true,
				"changeBPM": false,
				"bpm": 139
			},
			{
				"sectionNotes": [],
				"typeOfSection": 0,
				"lengthInSteps": 16,
				"gfSection": false,
				"altAnim": false,
				"mustHitSection": true,
				"changeBPM": false,
				"bpm": 139
			},
			{
				"sectionNotes": [],
				"typeOfSection": 0,
				"lengthInSteps": 16,
				"gfSection": false,
				"altAnim": false,
				"mustHitSection": true,
				"changeBPM": false,
				"bpm": 139
			},
			{
				"sectionNotes": [],
				"typeOfSection": 0,
				"lengthInSteps": 16,
				"gfSection": false,
				"altAnim": false,
				"mustHitSection": true,
				"changeBPM": false,
				"bpm": 139
			},
			{
				"sectionNotes": [],
				"typeOfSection": 0,
				"lengthInSteps": 16,
				"gfSection": false,
				"altAnim": false,
				"mustHitSection": true,
				"changeBPM": false,
				"bpm": 139
			},
			{
				"sectionNotes": [],
				"typeOfSection": 0,
				"lengthInSteps": 16,
				"gfSection": false,
				"altAnim": false,
				"mustHitSection": true,
				"changeBPM": false,
				"bpm": 139
			},
			{
				"sectionNotes": [],
				"typeOfSection": 0,
				"lengthInSteps": 16,
				"gfSection": false,
				"altAnim": false,
				"mustHitSection": true,
				"changeBPM": false,
				"bpm": 139
			},
			{
				"sectionNotes": [],
				"typeOfSection": 0,
				"lengthInSteps": 16,
				"gfSection": false,
				"altAnim": false,
				"mustHitSection": true,
				"changeBPM": false,
				"bpm": 139
			},
			{
				"sectionNotes": [],
				"typeOfSection": 0,
				"lengthInSteps": 16,
				"gfSection": false,
				"altAnim": false,
				"mustHitSection": true,
				"changeBPM": false,
				"bpm": 139
			},
			{
				"sectionNotes": [],
				"typeOfSection": 0,
				"lengthInSteps": 16,
				"gfSection": false,
				"altAnim": false,
				"mustHitSection": true,
				"changeBPM": false,
				"bpm": 139
			},
			{
				"sectionNotes": [],
				"typeOfSection": 0,
				"lengthInSteps": 16,
				"gfSection": false,
				"altAnim": false,
				"mustHitSection": true,
				"changeBPM": false,
				"bpm": 139
			},
			{
				"sectionNotes": [],
				"typeOfSection": 0,
				"lengthInSteps": 16,
				"gfSection": false,
				"altAnim": false,
				"mustHitSection": true,
				"changeBPM": false,
				"bpm": 139
			},
			{
				"sectionNotes": [],
				"typeOfSection": 0,
				"lengthInSteps": 16,
				"gfSection": false,
				"altAnim": false,
				"mustHitSection": true,
				"changeBPM": false,
				"bpm": 139
			},
			{
				"sectionNotes": [],
				"typeOfSection": 0,
				"lengthInSteps": 16,
				"gfSection": false,
				"altAnim": false,
				"mustHitSection": true,
				"changeBPM": false,
				"bpm": 139
			},
			{
				"sectionNotes": [],
				"typeOfSection": 0,
				"lengthInSteps": 16,
				"gfSection": false,
				"altAnim": false,
				"mustHitSection": true,
				"changeBPM": false,
				"bpm": 139
			},
			{
				"sectionNotes": [],
				"typeOfSection": 0,
				"lengthInSteps": 16,
				"gfSection": false,
				"altAnim": false,
				"mustHitSection": true,
				"changeBPM": false,
				"bpm": 139
			},
			{
				"sectionNotes": [],
				"typeOfSection": 0,
				"lengthInSteps": 16,
				"gfSection": false,
				"altAnim": false,
				"mustHitSection": true,
				"changeBPM": false,
				"bpm": 139
			},
			{
				"sectionNotes": [],
				"typeOfSection": 0,
				"lengthInSteps": 16,
				"gfSection": false,
				"altAnim": false,
				"mustHitSection": true,
				"changeBPM": false,
				"bpm": 139
			},
			{
				"gfSection": false,
				"lengthInSteps": 16,
				"altAnim": false,
				"typeOfSection": 0,
				"sectionNotes": [],
				"bpm": 139,
				"changeBPM": false,
				"mustHitSection": true
			},
			{
				"gfSection": false,
				"lengthInSteps": 16,
				"altAnim": false,
				"typeOfSection": 0,
				"sectionNotes": [],
				"bpm": 139,
				"changeBPM": false,
				"mustHitSection": true
			}
		],
		"gfVersion": "gf",
		"events": [
			[
				7122.30215827338,
				[
					[
						"Cam Note",
						"dad,950,1400",
						"80"
					]
				]
			],
			[
				7392.08633093525,
				[
					[
						"Cam Note",
						"bf,2850,1650",
						"80"
					]
				]
			],
			[
				7769.78417266187,
				[
					[
						"Set Cam Zoom",
						"0.5",
						""
					]
				]
			],
			[
				19856.1151079137,
				[
					[
						"Set Cam Zoom",
						"0.7",
						""
					],
					[
						"Add Camera Zoom",
						"0.015",
						"0.03"
					]
				]
			],
			[
				20179.8561151079,
				[
					[
						"Set Cam Zoom",
						"0.8",
						""
					],
					[
						"Add Camera Zoom",
						"0.015",
						"0.03"
					]
				]
			],
			[
				20503.5971223022,
				[
					[
						"Set Cam Zoom",
						"0.9",
						""
					],
					[
						"Add Camera Zoom",
						"0.015",
						"0.03"
					]
				]
			],
			[
				20827.3381294964,
				[
					[
						"Set Cam Zoom",
						"1",
						""
					],
					[
						"Add Camera Zoom",
						"0.015",
						"0.03"
					]
				]
			],
			[
				21151.0791366906,
				[
					[
						"Add Camera Zoom",
						"0.03",
						"0.06"
					],
					[
						"Set Cam Zoom",
						"0.5",
						""
					]
				]
			],
			[
				21366.9064748201,
				[
					[
						"Add Camera Zoom",
						"0.03",
						"0.06"
					]
				]
			],
			[
				21582.7338129496,
				[
					[
						"White Flash",
						"0.5",
						""
					]
				]
			],
			[
				33669.0647482015,
				[
					[
						"Add Camera Zoom",
						"",
						""
					]
				]
			],
			[
				33992.8057553957,
				[
					[
						"Add Camera Zoom",
						"",
						""
					]
				]
			],
			[
				34316.5467625899,
				[
					[
						"Add Camera Zoom",
						"",
						""
					]
				]
			],
			[
				34640.2877697842,
				[
					[
						"Add Camera Zoom",
						"",
						""
					]
				]
			],
			[
				34964.0287769784,
				[
					[
						"Add Camera Zoom",
						"",
						""
					]
				]
			],
			[
				35179.8561151079,
				[
					[
						"Add Camera Zoom",
						"",
						""
					]
				]
			],
			[
				37122.3021582734,
				[
					[
						"Set Cam Zoom",
						"0.7",
						""
					]
				]
			],
			[
				37553.9568345324,
				[
					[
						"Set Cam Zoom",
						"0.5",
						""
					],
					[
						"White Flash",
						"0.5",
						""
					]
				]
			],
			[
				40575.5395683453,
				[
					[
						"Set Cam Zoom",
						"0.7",
						""
					]
				]
			],
			[
				41007.1942446043,
				[
					[
						"Set Cam Zoom",
						"0.5",
						""
					]
				]
			],
			[
				44460.4316546763,
				[
					[
						"White Flash",
						"0.5",
						""
					]
				]
			],
			[
				50935.2517985612,
				[
					[
						"Set Cam Zoom",
						"0.55",
						""
					]
				]
			],
			[
				51285.9712230216,
				[
					[
						"Set Cam Zoom",
						"0.6",
						""
					]
				]
			],
			[
				51582.7338129497,
				[
					[
						"Set Cam Zoom",
						"0.7",
						""
					]
				]
			],
			[
				51798.5611510792,
				[
					[
						"Set Cam Zoom",
						"0.8",
						""
					]
				]
			],
			[
				52149.2805755396,
				[
					[
						"Set Cam Zoom",
						"0.9",
						""
					]
				]
			],
			[
				52446.0431654677,
				[
					[
						"Set Cam Zoom",
						"1",
						""
					]
				]
			],
			[
				52661.8705035972,
				[
					[
						"Set Cam Zoom",
						"0.5",
						""
					]
				]
			],
			[
				53525.1798561151,
				[
					[
						"Set Cam Zoom",
						"0.7",
						""
					]
				]
			],
			[
				53956.8345323741,
				[
					[
						"Set Cam Zoom",
						"0.5",
						""
					]
				]
			],
			[
				54388.4892086331,
				[
					[
						"Set Cam Zoom",
						"0.55",
						""
					]
				]
			],
			[
				54739.2086330936,
				[
					[
						"Set Cam Zoom",
						"0.6",
						""
					]
				]
			],
			[
				55035.9712230216,
				[
					[
						"Set Cam Zoom",
						"0.7",
						""
					]
				]
			],
			[
				55251.7985611511,
				[
					[
						"Set Cam Zoom",
						"0.8",
						""
					]
				]
			],
			[
				55602.5179856116,
				[
					[
						"Set Cam Zoom",
						"0.9",
						""
					]
				]
			],
			[
				55899.2805755396,
				[
					[
						"Set Cam Zoom",
						"1",
						""
					]
				]
			],
			[
				56115.1079136691,
				[
					[
						"Set Cam Zoom",
						"0.5",
						""
					]
				]
			],
			[
				56978.4172661871,
				[
					[
						"Set Cam Zoom",
						"0.7",
						""
					]
				]
			],
			[
				57410.0719424461,
				[
					[
						"Set Cam Zoom",
						"0.5",
						""
					]
				]
			],
			[
				57841.7266187051,
				[
					[
						"Set Cam Zoom",
						"0.5",
						""
					],
					[
						"Add Camera Zoom",
						"0.03",
						"0.06"
					]
				]
			],
			[
				58192.4460431655,
				[
					[
						"Add Camera Zoom",
						"0.03",
						"0.06"
					]
				]
			],
			[
				58489.2086330936,
				[
					[
						"Add Camera Zoom",
						"0.03",
						"0.06"
					]
				]
			],
			[
				58705.0359712231,
				[
					[
						"Add Camera Zoom",
						"0.03",
						"0.06"
					]
				]
			],
			[
				59028.7769784173,
				[
					[
						"Add Camera Zoom",
						"0.03",
						"0.06"
					]
				]
			],
			[
				59352.5179856116,
				[
					[
						"Add Camera Zoom",
						"0.03",
						"0.06"
					]
				]
			],
			[
				59568.3453237411,
				[
					[
						"Add Camera Zoom",
						"0.03",
						"0.06"
					]
				]
			],
			[
				59892.0863309353,
				[
					[
						"Add Camera Zoom",
						"0.03",
						"0.06"
					]
				]
			],
			[
				60215.8273381295,
				[
					[
						"Add Camera Zoom",
						"0.03",
						"0.06"
					]
				]
			],
			[
				60431.654676259,
				[
					[
						"Set Cam Zoom",
						"0.7",
						""
					]
				]
			],
			[
				60863.309352518,
				[
					[
						"Set Cam Zoom",
						"0.5",
						""
					]
				]
			],
			[
				61294.964028777,
				[
					[
						"Add Camera Zoom",
						"0.03",
						"0.06"
					],
					[
						"Set Cam Zoom",
						"0.6",
						""
					]
				]
			],
			[
				61618.7050359713,
				[
					[
						"Add Camera Zoom",
						"0.03",
						"0.06"
					],
					[
						"Set Cam Zoom",
						"0.7",
						""
					]
				]
			],
			[
				61942.4460431655,
				[
					[
						"Add Camera Zoom",
						"0.03",
						"0.06"
					],
					[
						"Set Cam Zoom",
						"0.8",
						""
					]
				]
			],
			[
				62158.273381295,
				[
					[
						"Add Camera Zoom",
						"0.03",
						"0.06"
					],
					[
						"Set Cam Zoom",
						"0.9",
						""
					]
				]
			],
			[
				62482.0143884893,
				[
					[
						"Add Camera Zoom",
						"0.03",
						"0.06"
					],
					[
						"Set Cam Zoom",
						"0.7",
						""
					]
				]
			],
			[
				62805.7553956835,
				[
					[
						"Add Camera Zoom",
						"0.03",
						"0.06"
					],
					[
						"Set Cam Zoom",
						"0.5",
						""
					]
				]
			],
			[
				63021.582733813,
				[
					[
						"Set Cam Zoom",
						"0.6",
						""
					]
				]
			],
			[
				63345.3237410072,
				[
					[
						"Set Cam Zoom",
						"0.7",
						""
					]
				]
			],
			[
				63669.0647482015,
				[
					[
						"Set Cam Zoom",
						"0.8",
						""
					]
				]
			],
			[
				63992.8057553957,
				[
					[
						"Set Cam Zoom",
						"0.9",
						""
					]
				]
			],
			[
				64316.54676259,
				[
					[
						"Set Cam Zoom",
						"0.5",
						""
					],
					[
						"Add Camera Zoom",
						"0.03",
						"0.06"
					]
				]
			],
			[
				64532.3741007195,
				[
					[
						"Add Camera Zoom",
						"0.03",
						"0.06"
					]
				]
			],
			[
				64748.201438849,
				[
					[
						"Set Cam Zoom",
						"0.8",
						""
					]
				]
			],
			[
				65179.856115108,
				[
					[
						"White Flash",
						"1",
						""
					],
					[
						"Set Cam Zoom",
						"0.5",
						""
					]
				]
			],
			[
				78561.1510791367,
				[
					[
						"Set Cam Zoom",
						"0.8",
						""
					]
				]
			],
			[
				78992.8057553957,
				[
					[
						"White Flash",
						"1",
						""
					],
					[
						"Set Cam Zoom",
						"0.5",
						""
					]
				]
			],
			[
				85467.6258992806,
				[
					[
						"Set Cam Zoom",
						"0.6",
						""
					]
				]
			],
			[
				87194.2446043166,
				[
					[
						"Set Cam Zoom",
						"0.65",
						""
					]
				]
			],
			[
				88920.8633093526,
				[
					[
						"Set Cam Zoom",
						"0.7",
						""
					]
				]
			],
			[
				90647.4820143886,
				[
					[
						"Set Cam Zoom",
						"0.75",
						""
					]
				]
			],
			[
				92374.1007194245,
				[
					[
						"Set Cam Zoom",
						"0.5",
						""
					]
				]
			],
			[
				100143.884892086,
				[
					[
						"Set Cam Zoom",
						"0.7",
						""
					]
				]
			],
			[
				101007.194244604,
				[
					[
						"Set Cam Zoom",
						"0.5",
						""
					]
				]
			],
			[
				101870.503597122,
				[
					[
						"Set Cam Zoom",
						"0.7",
						""
					]
				]
			],
			[
				102733.81294964,
				[
					[
						"Set Cam Zoom",
						"0.5",
						""
					]
				]
			],
			[
				106187.050359712,
				[
					[
						"Set Cam Zoom",
						"0.8",
						""
					]
				]
			],
			[
				106834.532374101,
				[
					[
						"Set Cam Zoom",
						"0.45",
						""
					]
				]
			]
		],
		"song": "System-Captured",
		"validScore": true,
		"needsVoices": true,
		"stage": "mainbg",
		"speed": 3,
		"bpm": 139
	}
}