{
	"song": {
		"player1": "codist",
		"events": [
			[
				57290.3225806452,
				[
					[
						"Change Character",
						"1",
						"kuu"
					]
				]
			],
			[
				61935.4838709678,
				[
					[
						"Snak BG",
						"",
						""
					]
				]
			]
		],
		"gfVersion": "jon",
		"notes": [
			{
				"sectionNotes": [],
				"lengthInSteps": 16,
				"mustHitSection": false
			},
			{
				"sectionNotes": [],
				"lengthInSteps": 16,
				"mustHitSection": false
			},
			{
				"sectionNotes": [],
				"lengthInSteps": 16,
				"mustHitSection": true
			},
			{
				"sectionNotes": [],
				"lengthInSteps": 16,
				"mustHitSection": true
			},
			{
				"sectionNotes": [
					[
						6580.64516129032,
						1,
						0
					],
					[
						6838.70967741936,
						3,
						0
					],
					[
						6967.74193548387,
						2,
						0
					],
					[
						7354.83870967742,
						0,
						0
					],
					[
						7612.90322580645,
						1,
						387.096774193548
					],
					[
						6193.54838709677,
						2,
						0
					]
				],
				"lengthInSteps": 16,
				"mustHitSection": false
			},
			{
				"sectionNotes": [
					[
						8129.03225806452,
						3,
						0
					],
					[
						8387.09677419355,
						1,
						0
					],
					[
						8516.12903225806,
						0,
						0
					],
					[
						8774.1935483871,
						1,
						0
					],
					[
						8903.22580645161,
						3,
						0
					],
					[
						9161.29032258065,
						1,
						0
					]
				],
				"lengthInSteps": 16,
				"mustHitSection": false
			},
			{
				"sectionNotes": [
					[
						9290.32258064516,
						2,
						0
					],
					[
						9677.41935483871,
						1,
						0
					],
					[
						9935.48387096774,
						0,
						0
					],
					[
						10064.5161290323,
						2,
						0
					],
					[
						10322.5806451613,
						3,
						0
					],
					[
						10709.6774193548,
						1,
						290.322580645161
					]
				],
				"lengthInSteps": 16,
				"mustHitSection": false
			},
			{
				"sectionNotes": [
					[
						11096.7741935484,
						3,
						0
					],
					[
						11225.8064516129,
						1,
						0
					],
					[
						11483.8709677419,
						1,
						0
					],
					[
						11612.9032258065,
						2,
						0
					],
					[
						11870.9677419355,
						3,
						0
					],
					[
						12000,
						0,
						0
					],
					[
						12258.064516129,
						1,
						0
					]
				],
				"lengthInSteps": 16,
				"mustHitSection": false
			},
			{
				"sectionNotes": [
					[
						12387.0967741935,
						6,
						677.41935483871
					],
					[
						12387.0967741935,
						2,
						0
					],
					[
						12774.1935483871,
						1,
						0
					],
					[
						13032.2580645161,
						3,
						0
					],
					[
						13161.2903225806,
						2,
						0
					],
					[
						13548.3870967742,
						3,
						0
					],
					[
						13806.4516129032,
						0,
						387.096774193548
					],
					[
						13548.3870967742,
						5,
						677.41935483871
					]
				],
				"lengthInSteps": 16,
				"mustHitSection": true
			},
			{
				"sectionNotes": [
					[
						15096.7741935484,
						2,
						0
					],
					[
						15354.8387096774,
						1,
						0
					],
					[
						14709.6774193548,
						0,
						0
					],
					[
						14967.7419354839,
						1,
						0
					],
					[
						14580.6451612903,
						1,
						0
					],
					[
						14322.5806451613,
						1,
						0
					],
					[
						14709.6774193548,
						4,
						677.41935483871
					]
				],
				"lengthInSteps": 16,
				"mustHitSection": true
			},
			{
				"sectionNotes": [
					[
						15483.8709677419,
						3,
						0
					],
					[
						15870.9677419355,
						1,
						0
					],
					[
						16258.064516129,
						1,
						0
					],
					[
						16129.0322580645,
						2,
						0
					],
					[
						16516.1290322581,
						0,
						0
					],
					[
						16903.2258064516,
						3,
						0
					],
					[
						15483.8709677419,
						7,
						677.41935483871
					]
				],
				"lengthInSteps": 16,
				"mustHitSection": true
			},
			{
				"sectionNotes": [
					[
						17032.2580645161,
						3,
						0
					],
					[
						17032.2580645161,
						5,
						0
					],
					[
						17161.2903225806,
						5,
						0
					],
					[
						17290.3225806452,
						6,
						0
					],
					[
						17419.3548387097,
						5,
						0
					],
					[
						17677.4193548387,
						4,
						193.548387096774
					],
					[
						17677.4193548387,
						3,
						0
					],
					[
						17806.4516129032,
						1,
						0
					],
					[
						18451.6129032258,
						1,
						0
					],
					[
						17290.3225806452,
						0,
						0
					],
					[
						17419.3548387097,
						3,
						0
					],
					[
						18064.5161290323,
						1,
						0
					],
					[
						18193.5483870968,
						0,
						0
					],
					[
						18064.5161290323,
						4,
						0
					],
					[
						18193.5483870968,
						6,
						0
					],
					[
						18451.6129032258,
						4,
						0
					]
				],
				"lengthInSteps": 16,
				"mustHitSection": true
			},
			{
				"sectionNotes": [
					[
						18580.6451612903,
						3,
						290.322580645161
					],
					[
						18967.7419354839,
						1,
						193.548387096774
					],
					[
						19225.8064516129,
						0,
						774.193548387097
					],
					[
						19612.9032258065,
						2,
						387.096774193548,
						"No Animation"
					]
				],
				"lengthInSteps": 16,
				"mustHitSection": false
			},
			{
				"sectionNotes": [
					[
						20129.0322580645,
						1,
						193.548387096774
					],
					[
						20516.1290322581,
						3,
						0
					],
					[
						21161.2903225806,
						1,
						387.096774193548
					],
					[
						20774.1935483871,
						0,
						290.322580645161
					]
				],
				"lengthInSteps": 16,
				"mustHitSection": false
			},
			{
				"sectionNotes": [
					[
						21677.4193548387,
						0,
						290.322580645161
					],
					[
						22064.5161290323,
						2,
						0
					],
					[
						22322.5806451613,
						0,
						387.096774193548
					],
					[
						22838.7096774194,
						3,
						290.322580645161
					]
				],
				"lengthInSteps": 16,
				"mustHitSection": false
			},
			{
				"sectionNotes": [
					[
						23225.8064516129,
						1,
						0
					],
					[
						23354.8387096774,
						1,
						0
					],
					[
						23483.8709677419,
						2,
						0
					],
					[
						23870.9677419355,
						3,
						0
					],
					[
						23612.9032258065,
						1,
						193.548387096774
					],
					[
						24258.064516129,
						1,
						0
					],
					[
						24387.0967741935,
						3,
						0
					],
					[
						24645.1612903226,
						1,
						0
					]
				],
				"lengthInSteps": 16,
				"mustHitSection": false
			},
			{
				"sectionNotes": [
					[
						24774.1935483871,
						6,
						1451.61290322581
					],
					[
						24774.1935483871,
						1,
						290.322580645161
					],
					[
						25161.2903225806,
						0,
						193.548387096774
					],
					[
						25419.3548387097,
						3,
						193.548387096774
					],
					[
						25806.4516129032,
						2,
						387.096774193548
					]
				],
				"lengthInSteps": 16,
				"mustHitSection": true
			},
			{
				"sectionNotes": [
					[
						26322.5806451613,
						3,
						290.322580645161
					],
					[
						26709.6774193548,
						1,
						0
					],
					[
						26967.7419354839,
						0,
						290.322580645161
					],
					[
						27354.8387096774,
						1,
						387.096774193548
					]
				],
				"lengthInSteps": 16,
				"mustHitSection": true
			},
			{
				"sectionNotes": [
					[
						27870.9677419355,
						2,
						290.322580645161
					],
					[
						28258.064516129,
						1,
						96.7741935483871
					],
					[
						28516.1290322581,
						2,
						387.096774193548
					],
					[
						29032.2580645161,
						1,
						290.322580645161
					]
				],
				"lengthInSteps": 16,
				"mustHitSection": true
			},
			{
				"sectionNotes": [
					[
						29419.3548387097,
						3,
						96.7741935483871
					],
					[
						29677.4193548387,
						2,
						0
					],
					[
						29806.4516129032,
						3,
						96.7741935483871
					],
					[
						30064.5161290323,
						1,
						0
					],
					[
						30451.6129032258,
						3,
						0
					],
					[
						30580.6451612903,
						1,
						0
					],
					[
						30838.7096774194,
						3,
						0
					]
				],
				"lengthInSteps": 16,
				"mustHitSection": true
			},
			{
				"sectionNotes": [
					[
						30967.7419354839,
						4,
						1451.61290322581
					]
				],
				"lengthInSteps": 16,
				"mustHitSection": false
			},
			{
				"sectionNotes": [],
				"lengthInSteps": 16,
				"mustHitSection": true
			},
			{
				"sectionNotes": [],
				"lengthInSteps": 16,
				"mustHitSection": false
			},
			{
				"sectionNotes": [],
				"lengthInSteps": 16,
				"mustHitSection": true
			},
			{
				"sectionNotes": [],
				"lengthInSteps": 16,
				"mustHitSection": false
			},
			{
				"sectionNotes": [],
				"lengthInSteps": 16,
				"mustHitSection": true
			},
			{
				"sectionNotes": [],
				"lengthInSteps": 16,
				"mustHitSection": false
			},
			{
				"sectionNotes": [],
				"lengthInSteps": 16,
				"mustHitSection": true
			},
			{
				"sectionNotes": [],
				"lengthInSteps": 16,
				"mustHitSection": false
			},
			{
				"sectionNotes": [],
				"lengthInSteps": 16,
				"mustHitSection": false
			},
			{
				"sectionNotes": [],
				"lengthInSteps": 16,
				"mustHitSection": true
			},
			{
				"sectionNotes": [],
				"lengthInSteps": 16,
				"mustHitSection": true
			},
			{
				"sectionNotes": [],
				"lengthInSteps": 16,
				"mustHitSection": false
			},
			{
				"sectionNotes": [],
				"lengthInSteps": 16,
				"mustHitSection": false
			},
			{
				"sectionNotes": [],
				"lengthInSteps": 16,
				"mustHitSection": true
			},
			{
				"sectionNotes": [],
				"lengthInSteps": 16,
				"mustHitSection": true
			},
			{
				"sectionNotes": [],
				"lengthInSteps": 16,
				"mustHitSection": true
			},
			{
				"sectionNotes": [],
				"lengthInSteps": 16,
				"mustHitSection": true
			},
			{
				"sectionNotes": [],
				"lengthInSteps": 16,
				"mustHitSection": true
			},
			{
				"sectionNotes": [],
				"lengthInSteps": 16,
				"mustHitSection": true
			},
			{
				"sectionNotes": [
					[
						61935.4838709678,
						2,
						0
					],
					[
						62064.5161290323,
						0,
						0
					],
					[
						62193.5483870968,
						2,
						0
					],
					[
						62322.5806451613,
						3,
						0
					],
					[
						62451.6129032259,
						1,
						0
					],
					[
						62580.6451612904,
						3,
						0
					],
					[
						62709.6774193549,
						0,
						96.7741935483871
					],
					[
						62967.7419354839,
						2,
						0
					],
					[
						63096.7741935484,
						3,
						96.7741935483871
					],
					[
						63354.8387096775,
						1,
						0
					]
				],
				"lengthInSteps": 16,
				"mustHitSection": false
			},
			{
				"sectionNotes": [
					[
						63483.870967742,
						7,
						1064.51612903226
					],
					[
						63483.870967742,
						3,
						0
					],
					[
						63612.9032258065,
						1,
						0
					],
					[
						63741.935483871,
						3,
						0
					],
					[
						63870.9677419355,
						0,
						0
					],
					[
						64000.0000000001,
						2,
						0
					],
					[
						64258.0645161291,
						1,
						0
					],
					[
						64129.0322580646,
						3,
						0
					],
					[
						64193.5483870968,
						2,
						0
					],
					[
						64387.0967741936,
						0,
						0
					],
					[
						64645.1612903226,
						2,
						0
					],
					[
						64774.1935483872,
						3,
						0
					],
					[
						64516.1290322581,
						1,
						0
					],
					[
						64903.2258064517,
						2,
						0
					]
				],
				"lengthInSteps": 16,
				"mustHitSection": true
			},
			{
				"typeOfSection": 0,
				"sectionNotes": [
					[
						65161.2903225807,
						0,
						0
					],
					[
						65032.2580645162,
						2,
						0
					],
					[
						65290.3225806452,
						2,
						0
					],
					[
						65419.3548387097,
						3,
						0
					],
					[
						65548.3870967743,
						1,
						0
					],
					[
						65677.4193548388,
						3,
						0
					],
					[
						65806.4516129033,
						0,
						0
					],
					[
						65935.4838709678,
						1,
						0
					],
					[
						66064.5161290323,
						0,
						0
					],
					[
						66193.5483870968,
						1,
						0
					],
					[
						66322.5806451614,
						3,
						0
					],
					[
						66451.6129032259,
						2,
						0
					],
					[
						65032.2580645162,
						5,
						1064.51612903226
					]
				],
				"sectionBeats": 4,
				"altAnim": false,
				"gfSection": false,
				"bpm": 120,
				"changeBPM": false,
				"mustHitSection": false
			},
			{
				"typeOfSection": 0,
				"sectionNotes": [
					[
						66580.6451612904,
						7,
						387.096774193548
					],
					[
						67096.7741935485,
						6,
						0
					],
					[
						67225.806451613,
						4,
						0
					],
					[
						67354.8387096775,
						5,
						290.322580645161
					],
					[
						67741.935483871,
						6,
						290.322580645161
					],
					[
						66580.6451612904,
						0,
						0
					],
					[
						66709.6774193549,
						1,
						0
					],
					[
						66838.7096774194,
						3,
						0
					],
					[
						66967.7419354839,
						1,
						0
					],
					[
						67096.7741935485,
						0,
						0
					],
					[
						67225.806451613,
						2,
						0
					],
					[
						67290.3225806452,
						3,
						0
					],
					[
						67354.8387096775,
						2,
						0
					],
					[
						67483.870967742,
						0,
						0
					],
					[
						67612.9032258065,
						1,
						0
					],
					[
						67870.9677419356,
						3,
						0
					],
					[
						67741.935483871,
						0,
						0
					],
					[
						68000.0000000001,
						1,
						0
					]
				],
				"sectionBeats": 4,
				"altAnim": false,
				"gfSection": false,
				"bpm": 155,
				"changeBPM": false,
				"mustHitSection": true
			},
			{
				"typeOfSection": 0,
				"sectionNotes": [
					[
						68129.0322580646,
						2,
						0
					],
					[
						68258.0645161291,
						0,
						0
					],
					[
						68387.0967741936,
						2,
						0
					],
					[
						68516.1290322581,
						3,
						0
					],
					[
						68645.1612903226,
						1,
						0
					],
					[
						68774.1935483872,
						3,
						0
					],
					[
						68903.2258064517,
						1,
						96.7741935483871
					],
					[
						69290.3225806452,
						1,
						96.7741935483871
					],
					[
						69161.2903225807,
						3,
						0
					],
					[
						69548.3870967743,
						0,
						0
					],
					[
						68129.0322580646,
						6,
						1064.51612903226
					]
				],
				"sectionBeats": 4,
				"altAnim": false,
				"gfSection": false,
				"bpm": 155,
				"changeBPM": false,
				"mustHitSection": false
			},
			{
				"typeOfSection": 0,
				"sectionNotes": [
					[
						69677.4193548388,
						5,
						1064.51612903226
					],
					[
						69677.4193548388,
						3,
						0
					],
					[
						69806.4516129033,
						1,
						0
					],
					[
						69935.4838709678,
						3,
						0
					],
					[
						70064.5161290323,
						0,
						0
					],
					[
						70193.5483870968,
						2,
						0
					],
					[
						70451.6129032259,
						1,
						0
					],
					[
						70322.5806451614,
						3,
						0
					],
					[
						70387.0967741936,
						2,
						0
					],
					[
						70580.6451612904,
						0,
						0
					],
					[
						70838.7096774194,
						2,
						0
					],
					[
						70967.7419354839,
						3,
						0
					],
					[
						70709.6774193549,
						1,
						0
					],
					[
						71096.7741935485,
						2,
						0
					]
				],
				"sectionBeats": 4,
				"altAnim": false,
				"gfSection": false,
				"bpm": 155,
				"changeBPM": false,
				"mustHitSection": true
			},
			{
				"typeOfSection": 0,
				"sectionNotes": [
					[
						71354.8387096775,
						0,
						0
					],
					[
						71225.806451613,
						2,
						0
					],
					[
						71483.870967742,
						2,
						0
					],
					[
						71612.9032258065,
						3,
						0
					],
					[
						71741.935483871,
						1,
						0
					],
					[
						71870.9677419355,
						3,
						0
					],
					[
						72000.0000000001,
						0,
						0
					],
					[
						72129.0322580646,
						1,
						0
					],
					[
						72258.0645161291,
						0,
						0
					],
					[
						72387.0967741936,
						1,
						0
					],
					[
						72516.1290322581,
						3,
						0
					],
					[
						72645.1612903226,
						2,
						0
					],
					[
						71225.806451613,
						5,
						1064.51612903226
					]
				],
				"sectionBeats": 4,
				"altAnim": false,
				"gfSection": false,
				"bpm": 155,
				"changeBPM": false,
				"mustHitSection": false
			},
			{
				"typeOfSection": 0,
				"sectionNotes": [
					[
						72774.1935483872,
						6,
						677.41935483871
					],
					[
						72774.1935483872,
						0,
						0
					],
					[
						72903.2258064517,
						1,
						0
					],
					[
						73032.2580645162,
						3,
						0
					],
					[
						73161.2903225807,
						1,
						0
					],
					[
						73290.3225806452,
						0,
						0
					],
					[
						73419.3548387097,
						2,
						0
					],
					[
						73483.870967742,
						3,
						0
					],
					[
						73548.3870967743,
						2,
						0
					],
					[
						73677.4193548388,
						0,
						0
					],
					[
						73806.4516129033,
						1,
						0
					],
					[
						74064.5161290323,
						3,
						0
					],
					[
						74193.5483870969,
						0,
						0
					],
					[
						73935.4838709678,
						2,
						0
					]
				],
				"sectionBeats": 4,
				"altAnim": false,
				"gfSection": false,
				"bpm": 155,
				"changeBPM": false,
				"mustHitSection": true
			},
			{
				"typeOfSection": 0,
				"sectionNotes": [
					[
						74322.5806451614,
						7,
						1064.51612903226
					],
					[
						74322.5806451614,
						1,
						0
					],
					[
						74580.6451612904,
						2,
						0
					],
					[
						74838.7096774194,
						3,
						0
					],
					[
						75096.7741935485,
						2,
						0
					],
					[
						75225.806451613,
						1,
						0
					],
					[
						75354.8387096775,
						0,
						0
					],
					[
						75741.9354838711,
						0,
						0
					],
					[
						75483.870967742,
						1,
						193.548387096774
					]
				],
				"sectionBeats": 4,
				"altAnim": false,
				"gfSection": false,
				"bpm": 155,
				"changeBPM": false,
				"mustHitSection": false
			},
			{
				"typeOfSection": 0,
				"sectionNotes": [
					[
						75870.9677419356,
						3,
						0
					],
					[
						76000.0000000001,
						1,
						0
					],
					[
						76129.0322580646,
						0,
						0
					],
					[
						76258.0645161291,
						1,
						0
					],
					[
						76387.0967741936,
						3,
						0
					],
					[
						76516.1290322581,
						0,
						0
					],
					[
						76645.1612903227,
						2,
						0
					],
					[
						76774.1935483872,
						1,
						0
					],
					[
						76903.2258064517,
						3,
						0
					],
					[
						77032.2580645162,
						2,
						0
					],
					[
						77161.2903225807,
						1,
						0
					],
					[
						77290.3225806453,
						3,
						0
					]
				],
				"sectionBeats": 4,
				"altAnim": false,
				"gfSection": false,
				"bpm": 155,
				"changeBPM": false,
				"mustHitSection": false
			},
			{
				"typeOfSection": 0,
				"sectionNotes": [
					[
						77419.3548387098,
						1,
						0
					],
					[
						77677.4193548388,
						2,
						0
					],
					[
						78193.5483870969,
						3,
						0
					],
					[
						78322.5806451614,
						1,
						0
					],
					[
						78451.6129032259,
						0,
						0
					],
					[
						78838.7096774195,
						0,
						0
					],
					[
						78580.6451612904,
						1,
						193.548387096774
					],
					[
						77419.3548387098,
						6,
						0
					],
					[
						77935.4838709678,
						1,
						0
					]
				],
				"sectionBeats": 4,
				"altAnim": false,
				"gfSection": false,
				"bpm": 155,
				"changeBPM": false,
				"mustHitSection": true
			},
			{
				"typeOfSection": 0,
				"sectionNotes": [
					[
						78967.741935484,
						3,
						0
					],
					[
						79096.7741935485,
						1,
						0
					],
					[
						79225.806451613,
						0,
						0
					],
					[
						79354.8387096775,
						1,
						0
					],
					[
						79483.870967742,
						3,
						0
					],
					[
						79612.9032258065,
						0,
						0
					],
					[
						80000.0000000001,
						3,
						0
					],
					[
						80129.0322580646,
						2,
						0
					],
					[
						80387.0967741936,
						3,
						0
					],
					[
						79870.9677419356,
						0,
						0
					],
					[
						80258.0645161291,
						0,
						0
					],
					[
						79741.9354838711,
						2,
						0
					],
					[
						80000.0000000001,
						5,
						0
					],
					[
						80129.0322580646,
						4,
						0
					],
					[
						80387.0967741936,
						7,
						0
					]
				],
				"sectionBeats": 4,
				"altAnim": false,
				"gfSection": false,
				"bpm": 155,
				"changeBPM": false,
				"mustHitSection": true
			},
			{
				"typeOfSection": 0,
				"sectionNotes": [
					[
						80516.1290322582,
						1,
						0
					],
					[
						80516.1290322582,
						7,
						290.322580645161
					],
					[
						81677.4193548388,
						1,
						193.548387096774
					],
					[
						81419.3548387098,
						1,
						0
					],
					[
						80774.1935483872,
						3,
						0
					],
					[
						81032.2580645162,
						0,
						0
					],
					[
						81290.3225806453,
						2,
						0
					],
					[
						81935.4838709678,
						3,
						0
					],
					[
						81548.3870967743,
						3,
						0
					]
				],
				"sectionBeats": 4,
				"altAnim": false,
				"gfSection": false,
				"bpm": 155,
				"changeBPM": false,
				"mustHitSection": true
			},
			{
				"typeOfSection": 0,
				"sectionNotes": [
					[
						82064.5161290324,
						0,
						0
					],
					[
						82193.5483870969,
						1,
						0
					],
					[
						82322.5806451614,
						0,
						0
					],
					[
						82451.6129032259,
						3,
						0
					],
					[
						82580.6451612904,
						2,
						0
					],
					[
						82709.6774193549,
						1,
						0
					],
					[
						82838.7096774195,
						0,
						0
					],
					[
						82967.741935484,
						1,
						0
					],
					[
						83096.7741935485,
						3,
						0
					],
					[
						83225.806451613,
						1,
						193.548387096774
					],
					[
						83483.870967742,
						2,
						0
					],
					[
						83483.870967742,
						5,
						0
					]
				],
				"sectionBeats": 4,
				"altAnim": false,
				"gfSection": false,
				"bpm": 155,
				"changeBPM": false,
				"mustHitSection": true
			},
			{
				"typeOfSection": 0,
				"sectionNotes": [
					[
						83612.9032258066,
						7,
						0
					],
					[
						83612.9032258066,
						2,
						0
					],
					[
						83870.9677419356,
						1,
						0
					],
					[
						84129.0322580646,
						3,
						0
					],
					[
						84387.0967741936,
						0,
						0
					],
					[
						84516.1290322582,
						2,
						0
					],
					[
						84645.1612903227,
						1,
						0
					],
					[
						84774.1935483872,
						3,
						193.548387096774
					],
					[
						85032.2580645162,
						1,
						0
					]
				],
				"sectionBeats": 4,
				"altAnim": false,
				"gfSection": false,
				"bpm": 155,
				"changeBPM": false,
				"mustHitSection": false
			},
			{
				"typeOfSection": 0,
				"sectionNotes": [
					[
						85161.2903225808,
						2,
						0
					],
					[
						85419.3548387098,
						2,
						0
					],
					[
						85161.2903225808,
						6,
						0
					],
					[
						85290.3225806453,
						7,
						0
					],
					[
						85419.3548387098,
						6,
						0
					],
					[
						85548.3870967743,
						4,
						0
					],
					[
						85290.3225806453,
						0,
						0
					],
					[
						85548.3870967743,
						3,
						0
					],
					[
						85806.4516129033,
						1,
						0
					],
					[
						85806.4516129033,
						5,
						0
					],
					[
						85935.4838709678,
						2,
						0
					],
					[
						85935.4838709678,
						6,
						0
					],
					[
						86064.5161290324,
						5,
						0
					],
					[
						86064.5161290324,
						1,
						0
					],
					[
						86193.5483870969,
						7,
						0
					],
					[
						86193.5483870969,
						3,
						0
					],
					[
						86322.5806451614,
						1,
						193.548387096774
					],
					[
						86322.5806451614,
						5,
						193.548387096774
					],
					[
						86580.6451612904,
						2,
						0
					],
					[
						85677.4193548388,
						0,
						0
					],
					[
						85677.4193548388,
						7,
						0
					],
					[
						86580.6451612904,
						7,
						0
					]
				],
				"sectionBeats": 4,
				"altAnim": false,
				"gfSection": false,
				"bpm": 155,
				"changeBPM": false,
				"mustHitSection": true
			},
			{
				"typeOfSection": 0,
				"sectionNotes": [
					[
						86709.6774193549,
						2,
						0
					],
					[
						86838.7096774195,
						0,
						0
					],
					[
						86967.741935484,
						2,
						0
					],
					[
						87096.7741935485,
						1,
						0
					],
					[
						87354.8387096775,
						3,
						193.548387096774
					],
					[
						87741.9354838711,
						2,
						0
					],
					[
						87870.9677419356,
						0,
						0
					],
					[
						88000.0000000001,
						2,
						0
					],
					[
						88129.0322580646,
						1,
						0
					]
				],
				"sectionBeats": 4,
				"altAnim": false,
				"gfSection": false,
				"bpm": 155,
				"changeBPM": false,
				"mustHitSection": false
			},
			{
				"typeOfSection": 0,
				"sectionNotes": [
					[
						88258.0645161291,
						3,
						0
					],
					[
						88516.1290322582,
						2,
						0
					],
					[
						88645.1612903227,
						3,
						0
					],
					[
						88903.2258064517,
						1,
						387.096774193548
					],
					[
						89419.3548387098,
						0,
						290.322580645161
					]
				],
				"sectionBeats": 4,
				"altAnim": false,
				"gfSection": false,
				"bpm": 155,
				"changeBPM": false,
				"mustHitSection": false
			},
			{
				"typeOfSection": 0,
				"sectionNotes": [
					[
						89806.4516129033,
						6,
						677.41935483871
					],
					[
						89806.4516129033,
						1,
						0
					],
					[
						90064.5161290324,
						1,
						0
					],
					[
						90193.5483870969,
						2,
						0
					],
					[
						90451.6129032259,
						2,
						0
					],
					[
						90580.6451612904,
						3,
						0
					],
					[
						89935.4838709679,
						0,
						0
					],
					[
						90322.5806451614,
						3,
						0
					],
					[
						90709.6774193549,
						1,
						0
					],
					[
						90838.7096774195,
						3,
						0
					],
					[
						90967.741935484,
						1,
						0
					],
					[
						91225.806451613,
						0,
						0
					]
				],
				"sectionBeats": 4,
				"altAnim": false,
				"gfSection": false,
				"bpm": 155,
				"changeBPM": false,
				"mustHitSection": true
			},
			{
				"typeOfSection": 0,
				"sectionNotes": [
					[
						91354.8387096775,
						3,
						0
					],
					[
						91612.9032258066,
						2,
						0
					],
					[
						91741.9354838711,
						3,
						0
					],
					[
						92516.1290322582,
						2,
						290.322580645161
					],
					[
						92000.0000000001,
						0,
						387.096774193548
					],
					[
						91354.8387096775,
						6,
						0
					],
					[
						91612.9032258066,
						5,
						0
					],
					[
						91741.9354838711,
						6,
						0
					],
					[
						92387.0967741937,
						5,
						0
					],
					[
						92000.0000000001,
						4,
						290.322580645161
					],
					[
						92516.1290322582,
						7,
						0
					],
					[
						92774.1935483872,
						5,
						0
					]
				],
				"sectionBeats": 4,
				"altAnim": false,
				"gfSection": false,
				"bpm": 155,
				"changeBPM": false,
				"mustHitSection": false
			},
			{
				"typeOfSection": 0,
				"sectionNotes": [
					[
						92903.2258064517,
						3,
						0
					],
					[
						93161.2903225808,
						1,
						0
					],
					[
						93290.3225806453,
						2,
						0
					],
					[
						93548.3870967743,
						1,
						0
					],
					[
						93677.4193548388,
						0,
						0
					],
					[
						93935.4838709679,
						3,
						0
					],
					[
						94193.5483870969,
						3,
						0
					],
					[
						94322.5806451614,
						1,
						0
					],
					[
						92903.2258064517,
						7,
						387.096774193548
					]
				],
				"sectionBeats": 4,
				"altAnim": false,
				"gfSection": false,
				"bpm": 155,
				"changeBPM": false,
				"mustHitSection": false
			},
			{
				"typeOfSection": 0,
				"sectionNotes": [
					[
						94451.6129032259,
						3,
						0
					],
					[
						94709.677419355,
						3,
						0
					],
					[
						94967.741935484,
						2,
						0
					],
					[
						95096.7741935485,
						1,
						0
					],
					[
						95225.806451613,
						0,
						0
					],
					[
						95483.8709677421,
						1,
						0
					],
					[
						95612.9032258066,
						2,
						0
					],
					[
						95870.9677419356,
						1,
						0
					]
				],
				"sectionBeats": 4,
				"altAnim": false,
				"gfSection": false,
				"bpm": 155,
				"changeBPM": false,
				"mustHitSection": false
			},
			{
				"typeOfSection": 0,
				"sectionNotes": [
					[
						96000.0000000001,
						7,
						0
					],
					[
						96258.0645161292,
						1,
						0
					],
					[
						96387.0967741937,
						0,
						0
					],
					[
						96000.0000000001,
						0,
						0
					],
					[
						96645.1612903227,
						3,
						0
					],
					[
						96774.1935483872,
						1,
						0
					],
					[
						97032.2580645163,
						3,
						0
					],
					[
						97290.3225806453,
						3,
						0
					],
					[
						97419.3548387098,
						1,
						0
					]
				],
				"sectionBeats": 4,
				"altAnim": false,
				"gfSection": false,
				"bpm": 155,
				"changeBPM": false,
				"mustHitSection": true
			},
			{
				"typeOfSection": 0,
				"sectionNotes": [
					[
						97548.3870967743,
						3,
						0
					],
					[
						97806.4516129034,
						3,
						0
					],
					[
						98064.5161290324,
						1,
						0
					],
					[
						98193.5483870969,
						0,
						0
					],
					[
						98322.5806451614,
						2,
						0
					],
					[
						98580.6451612905,
						1,
						0
					],
					[
						98709.677419355,
						3,
						0
					],
					[
						98967.741935484,
						1,
						0
					]
				],
				"sectionBeats": 4,
				"altAnim": false,
				"gfSection": false,
				"bpm": 155,
				"changeBPM": false,
				"mustHitSection": true
			},
			{
				"typeOfSection": 0,
				"sectionNotes": [
					[
						99096.7741935485,
						2,
						0
					],
					[
						99225.806451613,
						0,
						0
					],
					[
						99354.8387096775,
						2,
						0
					],
					[
						99483.870967742,
						1,
						0
					],
					[
						99741.9354838711,
						3,
						193.548387096774
					],
					[
						100129.032258065,
						2,
						0
					],
					[
						100258.064516129,
						0,
						0
					],
					[
						100516.129032258,
						1,
						0
					],
					[
						99096.7741935485,
						7,
						0
					]
				],
				"sectionBeats": 4,
				"altAnim": false,
				"gfSection": false,
				"bpm": 155,
				"changeBPM": false,
				"mustHitSection": false
			},
			{
				"typeOfSection": 0,
				"sectionNotes": [
					[
						100645.161290323,
						3,
						0
					],
					[
						100903.225806452,
						2,
						0
					],
					[
						101032.258064516,
						3,
						0
					],
					[
						101290.322580645,
						1,
						387.096774193548
					]
				],
				"sectionBeats": 4,
				"altAnim": false,
				"gfSection": false,
				"bpm": 155,
				"changeBPM": false,
				"mustHitSection": false
			},
			{
				"typeOfSection": 0,
				"sectionNotes": [
					[
						102193.548387097,
						1,
						0
					],
					[
						102451.612903226,
						1,
						0
					],
					[
						102580.64516129,
						2,
						0
					],
					[
						102838.709677419,
						2,
						0
					],
					[
						102967.741935484,
						3,
						0
					],
					[
						102322.580645161,
						0,
						0
					],
					[
						102709.677419355,
						3,
						0
					],
					[
						103096.774193548,
						1,
						0
					],
					[
						103225.806451613,
						3,
						0
					],
					[
						103354.838709678,
						1,
						0
					],
					[
						103612.903225807,
						0,
						0
					],
					[
						102193.548387097,
						5,
						0
					],
					[
						102451.612903226,
						5,
						0
					],
					[
						102580.64516129,
						6,
						0
					],
					[
						102838.709677419,
						6,
						0
					],
					[
						102967.741935484,
						7,
						0
					],
					[
						102322.580645161,
						4,
						0
					],
					[
						102709.677419355,
						7,
						0
					],
					[
						103096.774193548,
						5,
						0
					],
					[
						103225.806451613,
						7,
						0
					],
					[
						103354.838709678,
						5,
						0
					],
					[
						103612.903225807,
						4,
						0
					]
				],
				"sectionBeats": 4,
				"altAnim": false,
				"gfSection": false,
				"bpm": 155,
				"changeBPM": false,
				"mustHitSection": true
			},
			{
				"typeOfSection": 0,
				"sectionNotes": [
					[
						103741.935483871,
						3,
						0
					],
					[
						104000,
						2,
						0
					],
					[
						104129.032258065,
						3,
						0
					],
					[
						104387.096774194,
						0,
						387.096774193548
					],
					[
						103741.935483871,
						6,
						0
					],
					[
						104000,
						5,
						0
					],
					[
						104129.032258065,
						6,
						0
					],
					[
						104774.193548387,
						5,
						0
					],
					[
						104387.096774194,
						4,
						290.322580645161
					],
					[
						104903.225806452,
						7,
						0
					],
					[
						105161.290322581,
						5,
						0
					],
					[
						104258.064516129,
						5,
						0
					],
					[
						104258.064516129,
						1,
						0
					],
					[
						104903.225806452,
						1,
						0
					],
					[
						105161.290322581,
						3,
						0
					]
				],
				"sectionBeats": 4,
				"altAnim": false,
				"gfSection": false,
				"bpm": 155,
				"changeBPM": false,
				"mustHitSection": false
			},
			{
				"typeOfSection": 0,
				"sectionNotes": [
					[
						105290.322580645,
						6,
						290.322580645161
					],
					[
						105548.387096774,
						1,
						0
					],
					[
						105935.483870968,
						3,
						0
					],
					[
						106064.516129032,
						1,
						0
					],
					[
						106322.580645161,
						3,
						0
					],
					[
						105677.419354839,
						0,
						0
					],
					[
						105290.322580645,
						0,
						0
					],
					[
						106580.64516129,
						0,
						0
					],
					[
						106709.677419355,
						1,
						0
					]
				],
				"sectionBeats": 4,
				"altAnim": false,
				"gfSection": false,
				"bpm": 155,
				"changeBPM": false,
				"mustHitSection": true
			},
			{
				"typeOfSection": 0,
				"sectionNotes": [
					[
						106838.70967742,
						0,
						0
					],
					[
						107096.774193549,
						3,
						0
					],
					[
						107354.838709678,
						1,
						0
					],
					[
						107612.903225807,
						2,
						0
					],
					[
						107483.870967742,
						0,
						0
					],
					[
						107870.967741936,
						1,
						0
					],
					[
						108000,
						0,
						0
					],
					[
						108258.064516129,
						1,
						0
					],
					[
						108258.064516129,
						5,
						0
					]
				],
				"sectionBeats": 4,
				"altAnim": false,
				"gfSection": false,
				"bpm": 155,
				"changeBPM": false,
				"mustHitSection": true
			},
			{
				"typeOfSection": 0,
				"sectionNotes": [
					[
						108387.096774194,
						7,
						0
					],
					[
						109032.258064516,
						5,
						0
					],
					[
						109161.290322581,
						7,
						0
					],
					[
						108387.096774194,
						3,
						290.322580645161
					],
					[
						109032.258064516,
						1,
						0
					],
					[
						109161.290322581,
						3,
						290.322580645161
					],
					[
						109806.451612903,
						1,
						0
					]
				],
				"sectionBeats": 4,
				"altAnim": false,
				"gfSection": false,
				"bpm": 155,
				"changeBPM": false,
				"mustHitSection": true
			},
			{
				"typeOfSection": 0,
				"sectionNotes": [
					[
						109935.483870968,
						3,
						0
					],
					[
						110193.548387097,
						2,
						0
					],
					[
						110322.580645161,
						0,
						0
					],
					[
						110580.64516129,
						1,
						0
					]
				],
				"sectionBeats": 4,
				"altAnim": false,
				"gfSection": false,
				"bpm": 155,
				"changeBPM": false,
				"mustHitSection": true
			},
			{
				"typeOfSection": 0,
				"sectionNotes": [],
				"sectionBeats": 4,
				"altAnim": false,
				"gfSection": false,
				"bpm": 155,
				"changeBPM": false,
				"mustHitSection": false
			},
			{
				"typeOfSection": 0,
				"sectionNotes": [],
				"sectionBeats": 4,
				"altAnim": false,
				"gfSection": false,
				"bpm": 155,
				"changeBPM": false,
				"mustHitSection": false
			},
			{
				"typeOfSection": 0,
				"sectionNotes": [
					[
						114580.64516129,
						1,
						0
					],
					[
						114838.709677419,
						2,
						0
					],
					[
						115096.774193548,
						3,
						0
					],
					[
						115354.838709677,
						2,
						0
					],
					[
						115483.870967742,
						1,
						0
					],
					[
						115612.903225807,
						0,
						0
					],
					[
						116000,
						0,
						0
					],
					[
						115741.935483871,
						1,
						193.548387096774
					]
				],
				"sectionBeats": 4,
				"altAnim": false,
				"gfSection": false,
				"bpm": 155,
				"changeBPM": false,
				"mustHitSection": false
			},
			{
				"typeOfSection": 0,
				"sectionNotes": [
					[
						116129.032258065,
						3,
						0
					],
					[
						116258.064516129,
						1,
						0
					],
					[
						116387.096774194,
						0,
						0
					],
					[
						116516.129032258,
						1,
						0
					],
					[
						116645.161290323,
						3,
						0
					],
					[
						116774.193548387,
						0,
						0
					],
					[
						116903.225806452,
						2,
						0
					],
					[
						117032.258064516,
						1,
						0
					],
					[
						117161.290322581,
						3,
						0
					],
					[
						117290.322580645,
						2,
						0
					],
					[
						117419.35483871,
						1,
						0
					],
					[
						117548.387096774,
						3,
						0
					]
				],
				"sectionBeats": 4,
				"altAnim": false,
				"gfSection": false,
				"bpm": 155,
				"changeBPM": false,
				"mustHitSection": false
			},
			{
				"typeOfSection": 0,
				"sectionNotes": [
					[
						117677.419354839,
						1,
						0
					],
					[
						117935.483870968,
						2,
						0
					],
					[
						118451.612903226,
						3,
						0
					],
					[
						118580.64516129,
						1,
						0
					],
					[
						118709.677419355,
						0,
						0
					],
					[
						119096.774193548,
						0,
						0
					],
					[
						118838.709677419,
						1,
						193.548387096774
					],
					[
						117677.419354839,
						6,
						0
					],
					[
						118193.548387097,
						1,
						0
					]
				],
				"sectionBeats": 4,
				"altAnim": false,
				"gfSection": false,
				"bpm": 155,
				"changeBPM": false,
				"mustHitSection": true
			},
			{
				"typeOfSection": 0,
				"sectionNotes": [
					[
						119225.806451613,
						3,
						0
					],
					[
						119354.838709678,
						1,
						0
					],
					[
						119483.870967742,
						0,
						0
					],
					[
						119612.903225807,
						1,
						0
					],
					[
						119741.935483871,
						3,
						0
					],
					[
						119870.967741936,
						0,
						0
					],
					[
						120258.064516129,
						3,
						0
					],
					[
						120387.096774194,
						2,
						0
					],
					[
						120645.161290323,
						3,
						0
					],
					[
						120129.032258065,
						0,
						0
					],
					[
						120516.129032258,
						0,
						0
					],
					[
						120000,
						2,
						0
					],
					[
						120258.064516129,
						5,
						0
					],
					[
						120387.096774194,
						4,
						0
					],
					[
						120645.161290323,
						7,
						0
					]
				],
				"sectionBeats": 4,
				"altAnim": false,
				"gfSection": false,
				"bpm": 155,
				"changeBPM": false,
				"mustHitSection": true
			},
			{
				"typeOfSection": 0,
				"sectionNotes": [
					[
						120774.193548387,
						1,
						0
					],
					[
						120774.193548387,
						7,
						290.322580645161
					],
					[
						121935.483870968,
						1,
						193.548387096774
					],
					[
						121677.419354839,
						1,
						0
					],
					[
						121032.258064516,
						3,
						0
					],
					[
						121290.322580645,
						0,
						0
					],
					[
						121548.387096774,
						2,
						0
					],
					[
						122193.548387097,
						3,
						0
					],
					[
						121806.451612903,
						3,
						0
					]
				],
				"sectionBeats": 4,
				"altAnim": false,
				"gfSection": false,
				"bpm": 155,
				"changeBPM": false,
				"mustHitSection": true
			},
			{
				"typeOfSection": 0,
				"sectionNotes": [
					[
						122322.580645161,
						0,
						0
					],
					[
						122451.612903226,
						1,
						0
					],
					[
						122580.64516129,
						0,
						0
					],
					[
						122709.677419355,
						3,
						0
					],
					[
						122838.709677419,
						2,
						0
					],
					[
						122967.741935484,
						1,
						0
					],
					[
						123096.774193548,
						0,
						0
					],
					[
						123225.806451613,
						1,
						0
					],
					[
						123354.838709678,
						3,
						0
					],
					[
						123483.870967742,
						1,
						193.548387096774
					],
					[
						123741.935483871,
						2,
						0
					],
					[
						123741.935483871,
						5,
						0
					]
				],
				"sectionBeats": 4,
				"altAnim": false,
				"gfSection": false,
				"bpm": 155,
				"changeBPM": false,
				"mustHitSection": true
			},
			{
				"typeOfSection": 0,
				"sectionNotes": [
					[
						123870.967741936,
						7,
						0
					],
					[
						123870.967741936,
						2,
						0
					],
					[
						124129.032258065,
						1,
						0
					],
					[
						124387.096774194,
						3,
						0
					],
					[
						124645.161290323,
						0,
						0
					],
					[
						124774.193548387,
						2,
						0
					],
					[
						124903.225806452,
						1,
						0
					],
					[
						125032.258064516,
						3,
						193.548387096774
					],
					[
						125290.322580645,
						1,
						0
					]
				],
				"sectionBeats": 4,
				"altAnim": false,
				"gfSection": false,
				"bpm": 155,
				"changeBPM": false,
				"mustHitSection": false
			},
			{
				"typeOfSection": 0,
				"sectionNotes": [
					[
						125419.35483871,
						2,
						0
					],
					[
						125677.419354839,
						2,
						0
					],
					[
						125419.35483871,
						6,
						0
					],
					[
						125548.387096774,
						7,
						0
					],
					[
						125677.419354839,
						6,
						0
					],
					[
						125806.451612903,
						4,
						0
					],
					[
						125548.387096774,
						0,
						0
					],
					[
						125806.451612903,
						3,
						0
					],
					[
						126064.516129032,
						1,
						0
					],
					[
						126064.516129032,
						5,
						0
					],
					[
						126193.548387097,
						2,
						0
					],
					[
						125935.483870968,
						0,
						0
					],
					[
						125935.483870968,
						7,
						0
					],
					[
						126193.548387097,
						6,
						290.322580645161
					],
					[
						126322.580645161,
						3,
						0
					],
					[
						126451.612903226,
						2,
						0
					],
					[
						126580.645161291,
						1,
						0
					],
					[
						126838.70967742,
						1,
						0
					],
					[
						126709.677419355,
						3,
						0
					]
				],
				"sectionBeats": 4,
				"altAnim": false,
				"gfSection": false,
				"bpm": 155,
				"changeBPM": false,
				"mustHitSection": true
			},
			{
				"typeOfSection": 0,
				"sectionNotes": [
					[
						126967.741935484,
						4,
						290.322580645161
					],
					[
						126967.741935484,
						3,
						0
					],
					[
						127096.774193549,
						1,
						0
					],
					[
						127225.806451613,
						3,
						0
					],
					[
						127354.838709678,
						0,
						0
					],
					[
						127483.870967742,
						3,
						0
					],
					[
						127548.387096774,
						2,
						0
					],
					[
						127612.903225807,
						0,
						0
					],
					[
						127741.935483871,
						3,
						0
					],
					[
						127870.967741936,
						1,
						0
					],
					[
						128000,
						3,
						0
					],
					[
						128129.032258065,
						3,
						0
					],
					[
						128258.064516129,
						0,
						0
					],
					[
						128387.096774194,
						1,
						0
					]
				],
				"sectionBeats": 4,
				"altAnim": false,
				"gfSection": false,
				"bpm": 155,
				"changeBPM": false,
				"mustHitSection": false
			},
			{
				"typeOfSection": 0,
				"sectionNotes": [
					[
						128516.129032258,
						2,
						0
					],
					[
						128645.161290323,
						3,
						0
					],
					[
						128774.193548387,
						2,
						0
					],
					[
						129032.258064516,
						3,
						0
					],
					[
						128903.225806452,
						1,
						0
					],
					[
						129161.290322581,
						1,
						0
					],
					[
						129096.774193549,
						2,
						0
					],
					[
						129290.322580645,
						2,
						0
					],
					[
						129419.35483871,
						3,
						0
					],
					[
						129548.387096774,
						2,
						0
					],
					[
						129677.419354839,
						1,
						0
					],
					[
						129806.451612903,
						2,
						0
					],
					[
						129935.483870968,
						3,
						0
					]
				],
				"sectionBeats": 4,
				"altAnim": false,
				"gfSection": false,
				"bpm": 155,
				"changeBPM": false,
				"mustHitSection": false
			},
			{
				"typeOfSection": 0,
				"sectionNotes": [
					[
						130064.516129032,
						0,
						0
					],
					[
						130193.548387097,
						1,
						0
					],
					[
						130322.580645161,
						2,
						0
					],
					[
						130451.612903226,
						0,
						0
					],
					[
						130580.645161291,
						1,
						0
					],
					[
						130580.645161291,
						1,
						0
					],
					[
						130709.677419355,
						2,
						0
					],
					[
						130838.70967742,
						3,
						0
					],
					[
						130967.741935484,
						2,
						0
					],
					[
						131096.774193549,
						1,
						0
					],
					[
						131225.806451613,
						3,
						0
					],
					[
						131354.838709678,
						2,
						0
					],
					[
						131483.870967742,
						1,
						0
					]
				],
				"sectionBeats": 4,
				"altAnim": false,
				"gfSection": false,
				"bpm": 155,
				"changeBPM": false,
				"mustHitSection": false
			},
			{
				"typeOfSection": 0,
				"sectionNotes": [
					[
						131612.903225807,
						1,
						0
					],
					[
						131741.935483871,
						3,
						0
					],
					[
						131870.967741936,
						2,
						0
					],
					[
						132000,
						1,
						0
					],
					[
						132129.032258065,
						3,
						0
					],
					[
						132258.064516129,
						2,
						0
					],
					[
						132387.096774194,
						0,
						0
					],
					[
						132451.612903226,
						3,
						0
					],
					[
						132516.129032258,
						0,
						0
					],
					[
						132645.161290323,
						2,
						0
					],
					[
						132774.193548387,
						3,
						0
					],
					[
						132903.225806452,
						1,
						0
					],
					[
						132967.741935484,
						3,
						0
					],
					[
						133032.258064516,
						0,
						0
					]
				],
				"sectionBeats": 4,
				"altAnim": false,
				"gfSection": false,
				"bpm": 155,
				"changeBPM": false,
				"mustHitSection": false
			},
			{
				"typeOfSection": 0,
				"sectionNotes": [
					[
						133161.290322581,
						3,
						0
					],
					[
						133290.322580645,
						1,
						0
					],
					[
						133419.35483871,
						3,
						0
					],
					[
						133548.387096774,
						0,
						0
					],
					[
						133677.419354839,
						3,
						0
					],
					[
						133741.935483871,
						2,
						0
					],
					[
						133806.451612903,
						0,
						0
					],
					[
						133935.483870968,
						3,
						0
					],
					[
						134064.516129032,
						1,
						0
					],
					[
						134193.548387097,
						3,
						0
					],
					[
						134322.580645162,
						3,
						0
					],
					[
						134451.612903226,
						0,
						0
					],
					[
						134580.645161291,
						1,
						0
					],
					[
						133161.290322581,
						6,
						1451.61290322581
					]
				],
				"sectionBeats": 4,
				"altAnim": false,
				"gfSection": false,
				"bpm": 155,
				"changeBPM": false,
				"mustHitSection": true
			},
			{
				"typeOfSection": 0,
				"sectionNotes": [
					[
						134709.677419355,
						2,
						0
					],
					[
						134838.70967742,
						3,
						0
					],
					[
						134967.741935484,
						2,
						0
					],
					[
						135225.806451613,
						3,
						0
					],
					[
						135096.774193549,
						1,
						0
					],
					[
						135354.838709678,
						1,
						0
					],
					[
						135290.322580645,
						2,
						0
					],
					[
						135483.870967742,
						2,
						0
					],
					[
						135612.903225807,
						3,
						0
					],
					[
						135741.935483871,
						2,
						0
					],
					[
						135870.967741936,
						1,
						0
					],
					[
						136000,
						2,
						0
					],
					[
						136129.032258065,
						3,
						0
					]
				],
				"sectionBeats": 4,
				"altAnim": false,
				"gfSection": false,
				"bpm": 155,
				"changeBPM": false,
				"mustHitSection": true
			},
			{
				"typeOfSection": 0,
				"sectionNotes": [
					[
						136258.064516129,
						0,
						0
					],
					[
						136387.096774194,
						1,
						0
					],
					[
						136516.129032258,
						2,
						0
					],
					[
						136645.161290323,
						0,
						0
					],
					[
						136774.193548387,
						1,
						0
					],
					[
						136774.193548387,
						1,
						0
					],
					[
						136903.225806452,
						2,
						0
					],
					[
						137032.258064516,
						3,
						0
					],
					[
						137161.290322581,
						2,
						0
					],
					[
						137290.322580645,
						1,
						0
					],
					[
						137419.35483871,
						3,
						0
					],
					[
						137548.387096774,
						2,
						0
					],
					[
						137677.419354839,
						1,
						0
					],
					[
						136258.064516129,
						4,
						0
					],
					[
						136387.096774194,
						5,
						0
					],
					[
						136516.129032258,
						6,
						0
					],
					[
						136645.161290323,
						4,
						0
					],
					[
						136774.193548387,
						5,
						0
					],
					[
						136774.193548387,
						5,
						0
					],
					[
						136903.225806452,
						6,
						0
					],
					[
						137032.258064516,
						7,
						0
					],
					[
						137161.290322581,
						6,
						0
					],
					[
						137290.322580645,
						5,
						0
					],
					[
						137419.35483871,
						7,
						0
					],
					[
						137548.387096774,
						6,
						0
					],
					[
						137677.419354839,
						5,
						0
					]
				],
				"sectionBeats": 4,
				"altAnim": false,
				"gfSection": false,
				"bpm": 155,
				"changeBPM": false,
				"mustHitSection": true
			},
			{
				"typeOfSection": 0,
				"sectionNotes": [
					[
						137806.451612903,
						1,
						0
					],
					[
						137935.483870968,
						3,
						0
					],
					[
						138064.516129032,
						2,
						0
					],
					[
						138193.548387097,
						1,
						0
					],
					[
						138322.580645162,
						3,
						0
					],
					[
						138451.612903226,
						2,
						0
					],
					[
						138580.645161291,
						0,
						0
					],
					[
						138645.161290323,
						3,
						0
					],
					[
						138709.677419355,
						0,
						0
					],
					[
						138838.70967742,
						2,
						0
					],
					[
						138967.741935484,
						3,
						0
					],
					[
						139096.774193549,
						1,
						0
					],
					[
						139161.290322581,
						3,
						0
					],
					[
						139225.806451613,
						0,
						0
					],
					[
						137806.451612903,
						5,
						0
					],
					[
						137935.483870968,
						7,
						0
					],
					[
						138064.516129032,
						6,
						0
					],
					[
						138193.548387097,
						5,
						0
					],
					[
						138322.580645162,
						7,
						0
					],
					[
						138451.612903226,
						6,
						0
					],
					[
						138580.645161291,
						4,
						0
					],
					[
						138645.161290323,
						7,
						0
					],
					[
						138709.677419355,
						4,
						0
					],
					[
						138838.70967742,
						6,
						0
					],
					[
						138967.741935484,
						7,
						0
					],
					[
						139096.774193549,
						5,
						0
					],
					[
						139161.290322581,
						7,
						0
					],
					[
						139225.806451613,
						4,
						0
					]
				],
				"sectionBeats": 4,
				"altAnim": false,
				"gfSection": false,
				"bpm": 155,
				"changeBPM": false,
				"mustHitSection": true
			},
			{
				"typeOfSection": 0,
				"sectionNotes": [
					[
						139354.838709678,
						6,
						1451.61290322581
					],
					[
						139354.838709677,
						2,
						0
					],
					[
						139483.870967742,
						0,
						0
					],
					[
						139612.903225806,
						2,
						0
					],
					[
						139741.935483871,
						3,
						0
					],
					[
						139870.967741936,
						1,
						0
					],
					[
						140000,
						3,
						0
					],
					[
						140129.032258065,
						0,
						96.7741935483871
					],
					[
						140387.096774194,
						2,
						0
					],
					[
						140516.129032258,
						3,
						96.7741935483871
					],
					[
						140774.193548387,
						1,
						0
					]
				],
				"sectionBeats": 4,
				"altAnim": false,
				"gfSection": false,
				"bpm": 155,
				"changeBPM": false,
				"mustHitSection": false
			},
			{
				"typeOfSection": 0,
				"sectionNotes": [
					[
						140903.225806452,
						3,
						0
					],
					[
						141032.258064516,
						1,
						0
					],
					[
						141161.290322581,
						3,
						0
					],
					[
						141290.322580645,
						0,
						0
					],
					[
						141419.35483871,
						2,
						0
					],
					[
						141677.419354839,
						1,
						0
					],
					[
						141548.387096774,
						3,
						0
					],
					[
						141612.903225807,
						2,
						0
					],
					[
						141806.451612903,
						0,
						0
					],
					[
						142064.516129032,
						2,
						0
					],
					[
						142193.548387097,
						3,
						0
					],
					[
						141935.483870968,
						1,
						0
					],
					[
						142322.580645161,
						2,
						0
					],
					[
						140903.225806452,
						7,
						0
					]
				],
				"sectionBeats": 4,
				"altAnim": false,
				"gfSection": false,
				"bpm": 155,
				"changeBPM": false,
				"mustHitSection": true
			},
			{
				"typeOfSection": 0,
				"sectionNotes": [
					[
						142580.64516129,
						0,
						0
					],
					[
						142451.612903226,
						2,
						0
					],
					[
						142709.677419355,
						2,
						0
					],
					[
						142838.709677419,
						3,
						0
					],
					[
						142967.741935484,
						1,
						0
					],
					[
						143096.774193548,
						3,
						0
					],
					[
						143225.806451613,
						0,
						0
					],
					[
						143354.838709677,
						1,
						0
					],
					[
						143483.870967742,
						0,
						0
					],
					[
						143612.903225807,
						1,
						0
					],
					[
						143741.935483871,
						3,
						0
					],
					[
						143870.967741936,
						2,
						0
					],
					[
						142451.612903226,
						5,
						0
					]
				],
				"sectionBeats": 4,
				"altAnim": false,
				"gfSection": false,
				"bpm": 155,
				"changeBPM": false,
				"mustHitSection": false
			},
			{
				"typeOfSection": 0,
				"sectionNotes": [
					[
						144000,
						7,
						387.096774193548
					],
					[
						144516.129032258,
						6,
						0
					],
					[
						144645.161290323,
						4,
						0
					],
					[
						144774.193548387,
						5,
						290.322580645161
					],
					[
						145161.290322581,
						6,
						290.322580645161
					],
					[
						144000,
						0,
						0
					],
					[
						144129.032258065,
						1,
						0
					],
					[
						144258.064516129,
						3,
						0
					],
					[
						144387.096774194,
						1,
						0
					],
					[
						144516.129032258,
						0,
						0
					],
					[
						144645.161290323,
						2,
						0
					],
					[
						144709.677419355,
						3,
						0
					],
					[
						144774.193548387,
						2,
						0
					],
					[
						144903.225806452,
						0,
						0
					],
					[
						145032.258064516,
						1,
						0
					],
					[
						145290.322580645,
						3,
						0
					],
					[
						145161.290322581,
						0,
						0
					],
					[
						145419.35483871,
						1,
						0
					]
				],
				"sectionBeats": 4,
				"altAnim": false,
				"gfSection": false,
				"bpm": 155,
				"changeBPM": false,
				"mustHitSection": true
			},
			{
				"typeOfSection": 0,
				"sectionNotes": [
					[
						145548.387096774,
						2,
						0
					],
					[
						145677.419354839,
						0,
						0
					],
					[
						145806.451612903,
						2,
						0
					],
					[
						145935.483870968,
						3,
						0
					],
					[
						146064.516129032,
						1,
						0
					],
					[
						146193.548387097,
						3,
						0
					],
					[
						146322.580645161,
						1,
						96.7741935483871
					],
					[
						146709.677419355,
						1,
						96.7741935483871
					],
					[
						146580.64516129,
						3,
						0
					],
					[
						146967.741935484,
						0,
						0
					],
					[
						145548.387096774,
						6,
						1064.51612903226
					]
				],
				"sectionBeats": 4,
				"altAnim": false,
				"gfSection": false,
				"bpm": 155,
				"changeBPM": false,
				"mustHitSection": false
			},
			{
				"typeOfSection": 0,
				"sectionNotes": [
					[
						147096.774193548,
						3,
						0
					],
					[
						147225.806451613,
						1,
						0
					],
					[
						147354.838709677,
						3,
						0
					],
					[
						147483.870967742,
						0,
						0
					],
					[
						147612.903225807,
						2,
						0
					],
					[
						147870.967741936,
						1,
						0
					],
					[
						147741.935483871,
						3,
						0
					],
					[
						147806.451612903,
						2,
						0
					],
					[
						148000,
						0,
						0
					],
					[
						148258.064516129,
						2,
						0
					],
					[
						148387.096774194,
						3,
						0
					],
					[
						148129.032258065,
						1,
						0
					],
					[
						148516.129032258,
						2,
						0
					],
					[
						147096.774193548,
						7,
						0
					]
				],
				"sectionBeats": 4,
				"altAnim": false,
				"gfSection": false,
				"bpm": 155,
				"changeBPM": false,
				"mustHitSection": true
			},
			{
				"typeOfSection": 0,
				"sectionNotes": [
					[
						148774.193548387,
						0,
						0
					],
					[
						148645.161290323,
						2,
						0
					],
					[
						148903.225806452,
						2,
						0
					],
					[
						149032.258064516,
						3,
						0
					],
					[
						149161.290322581,
						1,
						0
					],
					[
						149290.322580645,
						3,
						0
					],
					[
						149419.35483871,
						0,
						0
					],
					[
						149548.387096774,
						1,
						0
					],
					[
						149677.419354839,
						0,
						0
					],
					[
						149806.451612903,
						1,
						0
					],
					[
						149935.483870968,
						3,
						0
					],
					[
						150064.516129032,
						2,
						0
					],
					[
						148645.161290323,
						5,
						290.322580645161
					]
				],
				"sectionBeats": 4,
				"altAnim": false,
				"gfSection": false,
				"bpm": 155,
				"changeBPM": false,
				"mustHitSection": false
			},
			{
				"typeOfSection": 0,
				"sectionNotes": [
					[
						150193.548387097,
						0,
						0
					],
					[
						150322.580645161,
						1,
						0
					],
					[
						150451.612903226,
						3,
						0
					],
					[
						150580.64516129,
						1,
						0
					],
					[
						150709.677419355,
						0,
						0
					],
					[
						150838.709677419,
						2,
						0
					],
					[
						150903.225806452,
						3,
						0
					],
					[
						150967.741935484,
						2,
						0
					],
					[
						151096.774193548,
						0,
						0
					],
					[
						151225.806451613,
						1,
						0
					],
					[
						151483.870967742,
						3,
						0
					],
					[
						151612.903225807,
						0,
						0
					],
					[
						151354.838709678,
						2,
						0
					],
					[
						150193.548387097,
						4,
						0
					],
					[
						150322.580645161,
						5,
						0
					],
					[
						150451.612903226,
						7,
						0
					],
					[
						150580.64516129,
						5,
						0
					],
					[
						150709.677419355,
						4,
						0
					],
					[
						150838.709677419,
						6,
						0
					],
					[
						150903.225806452,
						7,
						0
					],
					[
						150967.741935484,
						6,
						0
					],
					[
						151096.774193548,
						4,
						0
					],
					[
						151225.806451613,
						5,
						0
					],
					[
						151483.870967742,
						7,
						0
					],
					[
						151612.903225807,
						4,
						0
					],
					[
						151354.838709678,
						6,
						0
					]
				],
				"sectionBeats": 4,
				"altAnim": false,
				"gfSection": false,
				"bpm": 155,
				"changeBPM": false,
				"mustHitSection": true
			},
			{
				"typeOfSection": 0,
				"sectionNotes": [
					[
						151741.935483871,
						2,
						677.41935483871
					]
				],
				"sectionBeats": 4,
				"altAnim": false,
				"gfSection": false,
				"bpm": 155,
				"changeBPM": false,
				"mustHitSection": true
			},
			{
				"typeOfSection": 0,
				"sectionNotes": [],
				"sectionBeats": 4,
				"altAnim": false,
				"gfSection": false,
				"bpm": 155,
				"changeBPM": false,
				"mustHitSection": true
			},
			{
				"typeOfSection": 0,
				"sectionNotes": [],
				"sectionBeats": 4,
				"altAnim": false,
				"gfSection": false,
				"bpm": 155,
				"changeBPM": false,
				"mustHitSection": true
			},
			{
				"sectionBeats": 4,
				"sectionNotes": [],
				"typeOfSection": 0,
				"gfSection": false,
				"altAnim": false,
				"mustHitSection": true,
				"changeBPM": false,
				"bpm": 155
			},
			{
				"sectionBeats": 4,
				"sectionNotes": [],
				"typeOfSection": 0,
				"gfSection": false,
				"altAnim": false,
				"mustHitSection": true,
				"changeBPM": false,
				"bpm": 155
			},
			{
				"gfSection": false,
				"altAnim": false,
				"typeOfSection": 0,
				"sectionNotes": [],
				"bpm": 155,
				"sectionBeats": 4,
				"changeBPM": false,
				"mustHitSection": true
			}
		],
		"player2": "pico",
		"player3": null,
		"song": "The Snakkening",
		"arrowSkin": "",
		"stage": "snak",
		"needsVoices": true,
		"validScore": true,
		"bpm": 155,
		"speed": 3
	}
}